{
  "candidate_name": "NARA BHARATH REDDY",
  "party": "INC",
  "constituency": "BELLARY CITY",
  "state": "Karnataka",
  "status": "Winner",
  "affidavit_info": {
    "personal_details": {
      "s_o_d_o_w_o": "Nara Suryanarayana Reddy",
      "age": 33,
      "voter_enrolled_in": {
        "constituency": "94-Ballari City",
        "state": "Karnataka",
        "serial_no": 1452,
        "part_no": 101
      },
      "self_profession": "Business & Agriculturist",
      "spouse_profession": "Business, House Wife, Agriculturist"
    },
    "summary": {
      "criminal_cases_count": 2,
      "total_assets_in_rupees": 911821808,
      "total_liabilities_in_rupees": 343786368
    },
    "educational_details": {
      "category": "Graduate",
      "details": "BBM from Gulbarga University in 2010"
    },
    "income_tax_details": {
      "report_status": "No Problems in Reading Affidavit Information",
      "returns": [
        {
          "relation_type": "self",
          "pan_given": true,
          "financial_year": "2021 - 2022",
          "total_income_shown_in_itr_rupees": 4565420
        },
        {
          "relation_type": "self",
          "pan_given": true,
          "financial_year": "2020 - 2021",
          "total_income_shown_in_itr_rupees": 229980
        },
        {
          "relation_type": "self",
          "pan_given": true,
          "financial_year": "2019 - 2020",
          "total_income_shown_in_itr_rupees": 2311880
        },
        {
          "relation_type": "self",
          "pan_given": true,
          "financial_year": "2018 - 2019",
          "total_income_shown_in_itr_rupees": 71556
        },
        {
          "relation_type": "self",
          "pan_given": true,
          "financial_year": "2017 - 2018",
          "total_income_shown_in_itr_rupees": 4767711
        },
        {
          "relation_type": "spouse",
          "pan_given": true,
          "financial_year": "2021 - 2022",
          "total_income_shown_in_itr_rupees": 1121279
        },
        {
          "relation_type": "spouse",
          "pan_given": true,
          "financial_year": "2020 - 2021",
          "total_income_shown_in_itr_rupees": 201000
        },
        {
          "relation_type": "spouse",
          "pan_given": true,
          "financial_year": null,
          "total_income_shown_in_itr_rupees": 0
        },
        {
          "relation_type": "spouse",
          "pan_given": true,
          "financial_year": null,
          "total_income_shown_in_itr_rupees": 0
        },
        {
          "relation_type": "spouse",
          "pan_given": true,
          "financial_year": null,
          "total_income_shown_in_itr_rupees": 0
        },
        {
          "relation_type": "huf",
          "pan_given": false,
          "financial_year": null,
          "total_income_shown_in_itr_rupees": 0
        },
        {
          "relation_type": "huf",
          "pan_given": false,
          "financial_year": null,
          "total_income_shown_in_itr_rupees": 0
        },
        {
          "relation_type": "huf",
          "pan_given": false,
          "financial_year": null,
          "total_income_shown_in_itr_rupees": 0
        },
        {
          "relation_type": "huf",
          "pan_given": false,
          "financial_year": null,
          "total_income_shown_in_itr_rupees": 0
        },
        {
          "relation_type": "huf",
          "pan_given": false,
          "financial_year": null,
          "total_income_shown_in_itr_rupees": 0
        },
        {
          "relation_type": "dependent1",
          "pan_given": false,
          "financial_year": null,
          "total_income_shown_in_itr_rupees": 0
        },
        {
          "relation_type": "dependent1",
          "pan_given": false,
          "financial_year": null,
          "total_income_shown_in_itr_rupees": 0
        },
        {
          "relation_type": "dependent1",
          "pan_given": false,
          "financial_year": null,
          "total_income_shown_in_itr_rupees": 0
        },
        {
          "relation_type": "dependent1",
          "pan_given": false,
          "financial_year": null,
          "total_income_shown_in_itr_rupees": 0
        },
        {
          "relation_type": "dependent1",
          "pan_given": false,
          "financial_year": null,
          "total_income_shown_in_itr_rupees": 0
        },
        {
          "relation_type": "dependent2",
          "pan_given": false,
          "financial_year": null,
          "total_income_shown_in_itr_rupees": 0
        },
        {
          "relation_type": "dependent2",
          "pan_given": false,
          "financial_year": null,
          "total_income_shown_in_itr_rupees": 0
        },
        {
          "relation_type": "dependent2",
          "pan_given": false,
          "financial_year": null,
          "total_income_shown_in_itr_rupees": 0
        },
        {
          "relation_type": "dependent2",
          "pan_given": false,
          "financial_year": null,
          "total_income_shown_in_itr_rupees": 0
        },
        {
          "relation_type": "dependent2",
          "pan_given": false,
          "financial_year": null,
          "total_income_shown_in_itr_rupees": 0
        },
        {
          "relation_type": "dependent3",
          "pan_given": false,
          "financial_year": null,
          "total_income_shown_in_itr_rupees": 0
        },
        {
          "relation_type": "dependent3",
          "pan_given": false,
          "financial_year": null,
          "total_income_shown_in_itr_rupees": 0
        },
        {
          "relation_type": "dependent3",
          "pan_given": false,
          "financial_year": null,
          "total_income_shown_in_itr_rupees": 0
        },
        {
          "relation_type": "dependent3",
          "pan_given": false,
          "financial_year": null,
          "total_income_shown_in_itr_rupees": 0
        },
        {
          "relation_type": "dependent3",
          "pan_given": false,
          "financial_year": null,
          "total_income_shown_in_itr_rupees": 0
        }
      ]
    },
    "criminal_cases": {
      "report_status": "No Problems in Reading Affidavit Information",
      "brief_details_ipc_bns": [
        {
          "charges_related_to": "Putting person in fear of accusation of offence, in order to commit extortion",
          "ipc_section": "389",
          "count": 1
        },
        {
          "charges_related_to": "Punishment for criminal intimidation",
          "ipc_section": "506",
          "count": 1
        },
        {
          "charges_related_to": "Cheating and dishonestly inducing delivery of property",
          "ipc_section": "420",
          "count": 1
        },
        {
          "charges_related_to": "Forgery for purpose of cheating",
          "ipc_section": "468",
          "count": 1
        },
        {
          "charges_related_to": "Punishment for criminal breach of trust",
          "ipc_section": "406",
          "count": 1
        },
        {
          "charges_related_to": "Giving false evidence",
          "ipc_section": "191",
          "count": 1
        },
        {
          "charges_related_to": "Fabricating false evidence",
          "ipc_section": "192",
          "count": 1
        },
        {
          "charges_related_to": "Punishment of criminal conspiracy",
          "ipc_section": "120B",
          "count": 1
        },
        {
          "charges_related_to": "Acts done by several persons in furtherance of common intention",
          "ipc_section": "34",
          "count": 1
        },
        {
          "charges_related_to": "Punishment for forgery",
          "ipc_section": "465",
          "count": 1
        },
        {
          "charges_related_to": "Using as genuine a forged document or electronic record",
          "ipc_section": "471",
          "count": 1
        },
        {
          "charges_related_to": "Abettor present when offence is committed",
          "ipc_section": "114",
          "count": 1
        },
        {
          "charges_related_to": "False information, with intent to cause public servant to use his lawful power to the injury of another person",
          "ipc_section": "182",
          "count": 1
        }
      ],
      "pending_cases": [
        {
          "serial_no": 1,
          "fir_no": "0024/2023, N. Bharath Reddy (A2) & Others, Gandhi Nagar Police Station, Ballari",
          "case_no": null,
          "court": "Principal Civil Judge (Jr.Dn) JMFC Court, Ballari",
          "ipc_sections_applicable": "389, 506, 120B, 34",
          "other_details_or_acts_sections_applicable": "Not yet filed charge sheet , still it is in investigation stage",
          "charges_framed": false,
          "date_on_which_charges_were_framed": null,
          "appeal_filed": false,
          "details_and_present_status_of_appeal": null
        },
        {
          "serial_no": 2,
          "fir_no": "PCR No-74/2022",
          "case_no": null,
          "court": "Principal Civil Judge (Jr.Dn) JMFC Court, Ballari",
          "ipc_sections_applicable": "420, 465, 468, 471, 406, 114, 182, 191, 192",
          "other_details_or_acts_sections_applicable": null,
          "charges_framed": false,
          "date_on_which_charges_were_framed": null,
          "appeal_filed": true,
          "details_and_present_status_appeal": "Against the 156(3) order CRPL Petition No-100893/2022, Filed and the same is Stayed by the Honourable High Court of Karnataka, Dharwad"
        }
      ],
      "convicted_cases": []
    },
    "movable_assets": {
      "report_status": "No Problems in Reading Affidavit Information",
      "gross_total_value_self_rupees": 203237176,
      "gross_total_value_spouse_rupees": 49644965,
      "gross_total_value_huf_rupees": 0,
      "gross_total_value_dependent1_rupees": 0,
      "gross_total_value_dependent2_rupees": 0,
      "gross_total_value_dependent3_rupees": 0,
      "gross_total_value_total_rupees": 252882141,
      "items": [
        {
          "sr_no": "i",
          "description": "Cash",
          "self_value_rupees": 392000,
          "spouse_value_rupees": 1054000,
          "huf_value_rupees": 0,
          "dependent1_value_rupees": 0,
          "dependent2_value_rupees": 0,
          "dependent3_value_rupees": 0,
          "total_value_rupees": 1446000,
          "self_details": {
            "amount_rupees": 392000
          },
          "spouse_details": {
            "amount_rupees": 1054000
          }
        },
        {
          "sr_no": "ii",
          "description": "Deposits in Banks, Financial Institutions and Non-Banking Financial Companies",
          "self_value_rupees": 1787299,
          "spouse_value_rupees": 6592465,
          "huf_value_rupees": 0,
          "dependent1_value_rupees": 0,
          "dependent2_value_rupees": 0,
          "dependent3_value_rupees": 0,
          "total_value_rupees": 8379764,
          "self_details": [
            {
              "bank": "SBI Commercial Br. Bellary",
              "account_no": "1044491xxxxx",
              "amount_rupees": 139482
            },
            {
              "bank": "Karnataka Gramin Bank",
              "account_no": "1060510100xxxxx",
              "amount_rupees": 30037
            },
            {
              "bank": "Syndicate Bank, Z.P. Br.",
              "account_no": "0623201001xxxxx",
              "amount_rupees": 31700
            },
            {
              "bank": "HDFC Bank, Ltd Kappagal Road, Br. Ballari",
              "account_no": "5910805999xxxxx",
              "amount_rupees": 852646
            },
            {
              "bank": "HDFC Bank Ltd, Kappagal Road, Ballari",
              "account_no": "189999999xxxxx",
              "amount_rupees": 75259
            },
            {
              "bank": "Ballari District Co-Operative Central Bank, Ballari",
              "account_no": "2001610100xxxxx",
              "amount_rupees": 1000
            },
            {
              "bank": "Standard Chartered Bank, Bengaluru",
              "account_no": "4561163xxxxx",
              "amount_rupees": 25000
            },
            {
              "bank": "Karnataka Gramin Bank, Gandhi Nagar Br. Ballari",
              "account_no": "1060510109xxxxx",
              "amount_rupees": 20000
            },
            {
              "bank": "HDFC Bank Ltd, Ballari FDR",
              "account_no": "5030057286xxxxx",
              "amount_rupees": 379537
            }
          ],
          "spouse_details": [
            {
              "bank": "Axis Bank Ltd, College road, Hospet",
              "account_no": "921010047xxxxx",
              "amount_rupees": 2152266
            },
            {
              "bank": "HDFC Bank Ltd, College Road hospet",
              "account_no": "1761153000xxxxx",
              "amount_rupees": 524672
            },
            {
              "bank": "ICICI Bank Ltd, College Road, Hospet",
              "account_no": "10730150xxxxx",
              "amount_rupees": 3680672
            },
            {
              "bank": "IDBI Bank Ltd, College road hospet",
              "account_no": "10391040001xxxxx",
              "amount_rupees": 63855
            }
          ]
        },
        {
          "sr_no": "iii",
          "description": "Bonds, Debentures and Shares in companies",
          "self_value_rupees": 5462208,
          "spouse_value_rupees": 0,
          "huf_value_rupees": 0,
          "dependent1_value_rupees": 0,
          "dependent2_value_rupees": 0,
          "dependent3_value_rupees": 0,
          "total_value_rupees": 5462208,
          "self_details": [
            {
              "company": "Raghavendra Granites",
              "amount_rupees": 42819
            },
            {
              "company": "Nara Bros Properties LLP",
              "amount_rupees": 5419389
            }
          ],
          "spouse_details": [
            {
              "company": "Sri Krishna Vyjayanthi Industries",
              "amount_rupees": -5825333
            }
          ]
        },
        {
          "sr_no": "iv",
          "description": "(a) NSS, Postal Savings etc",
          "self_value_rupees": 0,
          "spouse_value_rupees": 0,
          "huf_value_rupees": 0,
          "dependent1_value_rupees": 0,
          "dependent2_value_rupees": 0,
          "dependent3_value_rupees": 0,
          "total_value_rupees": 0,
          "self_details": "Nil",
          "spouse_details": "Nil"
        },
        {
          "sr_no": null,
          "description": "(b) LIC or other insurance Policies",
          "self_value_rupees": 0,
          "spouse_value_rupees": 0,
          "huf_value_rupees": 0,
          "dependent1_value_rupees": 0,
          "dependent2_value_rupees": 0,
          "dependent3_value_rupees": 0,
          "total_value_rupees": 0,
          "self_details": "Nil",
          "spouse_details": "Nil"
        },
        {
          "sr_no": "v",
          "description": "Personal loans/advance given",
          "self_value_rupees": 172909316,
          "spouse_value_rupees": 0,
          "huf_value_rupees": 0,
          "dependent1_value_rupees": 0,
          "dependent2_value_rupees": 0,
          "dependent3_value_rupees": 0,
          "total_value_rupees": 172909316,
          "self_details": [
            {
              "name": "Jupiter Telecom Services",
              "amount_rupees": 450000
            },
            {
              "name": "Manoja Rathnababau",
              "amount_rupees": 187000
            },
            {
              "name": "Monika & Sonika Enterprises",
              "amount_rupees": 338688
            },
            {
              "name": "PNR Infra A/c",
              "amount_rupees": 335000
            },
            {
              "name": "Prabhanjan",
              "amount_rupees": 150000
            },
            {
              "name": "Rathnababau",
              "amount_rupees": 2709555
            },
            {
              "name": "S.B. Projects",
              "amount_rupees": 1764600
            },
            {
              "name": "Vyjayanthi Reddy",
              "amount_rupees": 150000000
            },
            {
              "name": "Sridhar.K",
              "amount_rupees": 1000000
            },
            {
              "name": "Satish Reddy",
              "amount_rupees": 300000
            },
            {
              "name": "Recovery Officer DRT, Bengaluru",
              "amount_rupees": 6000000
            },
            {
              "name": "Sun Minerals Madagascar",
              "amount_rupees": 9289537
            },
            {
              "name": "Sainath",
              "amount_rupees": 384936
            }
          ],
          "spouse_details": "Nil"
        },
        {
          "sr_no": "vi",
          "description": "Motor Vehicles (details of make, etc.)",
          "self_value_rupees": 6768991,
          "spouse_value_rupees": 15265000,
          "huf_value_rupees": 0,
          "dependent1_value_rupees": 0,
          "dependent2_value_rupees": 0,
          "dependent3_value_rupees": 0,
          "total_value_rupees": 22033991,
          "self_details": [
            {
              "make": "Mahindra Thar",
              "registration_no": "Ka46N9009",
              "year": 2020,
              "amount_rupees": 1689994
            },
            {
              "make": "Toyota Fortuner",
              "registration_no": "KA69N9009",
              "year": 2022,
              "amount_rupees": 5078997
            }
          ],
          "spouse_details": [
            {
              "make": "Toyota Vellfire",
              "registration_no": "KA35MC9919",
              "year": 2022,
              "amount_rupees": 9080000
            },
            {
              "make": "Wrangler",
              "registration_no": "KA35Mc1999",
              "year": 2022,
              "amount_rupees": 6185000
            }
          ]
        },
        {
          "sr_no": "vii",
          "description": "Jewellery (give details weight value)",
          "self_value_rupees": 16150000,
          "spouse_value_rupees": 26904500,
          "huf_value_rupees": 0,
          "dependent1_value_rupees": 0,
          "dependent2_value_rupees": 0,
          "dependent3_value_rupees": 0,
          "total_value_rupees": 43054500,
          "self_details": [
            {
              "type": "Gold & Diamond",
              "carats": 119.35,
              "grams": 1885.83,
              "amount_rupees": 15100000
            },
            {
              "type": "Silver Articles",
              "kgs": 10.152,
              "amount_rupees": 1050000
            }
          ],
          "spouse_details": [
            {
              "type": "Gold & Diamond",
              "carats": 52.10,
              "grams": 3750,
              "amount_rupees": 22382000
            },
            {
              "type": "Silver Articles",
              "kgs": 50.25,
              "amount_rupees": 4522500
            }
          ]
        },
        {
          "sr_no": "viii",
          "description": "Other assets, such as values of claims / interests",
          "self_value_rupees": 0,
          "spouse_value_rupees": 0,
          "huf_value_rupees": 0,
          "dependent1_value_rupees": 0,
          "dependent2_value_rupees": 0,
          "dependent3_value_rupees": 0,
          "total_value_rupees": 0,
          "self_details": "Nil",
          "spouse_details": "Nil"
        }
      ]
    },
    "immovable_assets": {
      "report_status": "No Problems in Reading Affidavit Information",
      "total_current_market_value_self_rupees": 641343000,
      "total_current_market_value_spouse_rupees": 13240000,
      "total_current_market_value_huf_rupees": 10182000,
      "total_current_market_value_dependent1_rupees": 0,
      "total_current_market_value_dependent2_rupees": 0,
      "total_current_market_value_dependent3_rupees": 0,
      "total_current_market_value_total_rupees": 664765000,
      "items": [
        {
          "sr_no": "i",
          "description": "Agricultural Land",
          "self_value_rupees": 19488000,
          "spouse_value_rupees": 6040000,
          "huf_value_rupees": 99820000,
          "dependent1_value_rupees": 0,
          "dependent2_value_rupees": 0,
          "dependent3_value_rupees": 0,
          "total_value_rupees": 125340000,
          "self_details": [
            {
              "location": "Halkundi",
              "sy_no": "122A",
              "total_area_acres": 3.69,
              "built_up_area": null,
              "inherited": false,
              "purchase_date": "2007-12-22",
              "purchase_cost_rupees": 404240,
              "development_cost_rupees": 369535,
              "current_value_rupees": 2140000
            },
            {
              "location": "Halkundi",
              "sy_no": "122B & C",
              "total_area_acres": 2.91,
              "built_up_area": null,
              "inherited": false,
              "purchase_date": "2007-12-22",
              "purchase_cost_rupees": 318930,
              "development_cost_rupees": 291422,
              "current_value_rupees": 1688000
            },
            {
              "location": "Ballari",
              "sy_no": "639/A1/E2",
              "total_area_acres": 0.37,
              "built_up_area": null,
              "inherited": false,
              "purchase_date": "2010-04-30",
              "purchase_cost_rupees": 439243,
              "development_cost_rupees": 0,
              "current_value_rupees": 1140000
            },
            {
              "location": "Lakshmipura (v)",
              "sy_no": "194/2",
              "total_area_acres": 1.17,
              "built_up_area": null,
              "inherited": false,
              "purchase_date": "2015-05-26",
              "purchase_cost_rupees": 1030770,
              "development_cost_rupees": 0,
              "current_value_rupees": 1400000
            },
            {
              "location": "Karavadi (v)",
              "sy_no": "353/2",
              "total_area_acres": 3.02,
              "built_up_area": null,
              "inherited": false,
              "purchase_date": "2017-04-03",
              "purchase_cost_rupees": 1623517,
              "development_cost_rupees": 0,
              "current_value_rupees": 1900000
            },
            {
              "location": "Gowral (v)",
              "sy_no": "35/3",
              "total_area_acres": 10.00,
              "built_up_area": null,
              "inherited": false,
              "purchase_date": "2012-08-06",
              "purchase_cost_rupees": 509400,
              "development_cost_rupees": 0,
              "current_value_rupees": 2500000
            },
            {
              "location": "Nallacheruvu (v)",
              "sy_no": "1000,1014,1015",
              "total_area_acres": 11.43,
              "built_up_area": null,
              "inherited": false,
              "purchase_date": "2016-06-06",
              "purchase_cost_rupees": 1065220,
              "development_cost_rupees": 0,
              "current_value_rupees": 1800000
            },
            {
              "location": "Ginigera (v)",
              "sy_no": "272/2 & 3",
              "total_area_acres": 7.07,
              "built_up_area": null,
              "inherited": false,
              "purchase_date": "2021-11-06",
              "purchase_cost_rupees": 4604980,
              "development_cost_rupees": 0,
              "current_value_rupees": 7200000
            },
            {
              "location": "Ballari (R)",
              "sy_no": "639/25, 29",
              "total_area_acres": 0.91,
              "built_up_area": null,
              "inherited": false,
              "purchase_date": "2021-10-07",
              "purchase_cost_rupees": 2605700,
              "development_cost_rupees": 0,
              "current_value_rupees": 2750000
            }
          ],
          "spouse_details": [
            {
              "location": "Kechchinabandi (v), H.B. Halli Tq",
              "sy_no": "45A/1",
              "total_area_acres": 4.29,
              "built_up_area": null,
              "inherited": false,
              "purchase_date": "2015-11-09",
              "purchase_cost_rupees": 436680,
              "development_cost_rupees": 0,
              "current_value_rupees": 2145000
            },
            {
              "location": "Kechchinabandi (v), H.B. Halli Tq",
              "sy_no": "44/B",
              "total_area_acres": 0.88,
              "built_up_area": null,
              "inherited": false,
              "purchase_date": "2015-11-09",
              "purchase_cost_rupees": 89175,
              "development_cost_rupees": 0,
              "current_value_rupees": 440000
            },
            {
              "location": "Kechchinabandi (v), H.B. Halli Tq",
              "sy_no": "44/A",
              "total_area_acres": 0.63,
              "built_up_area": null,
              "inherited": false,
              "purchase_date": "2015-11-09",
              "purchase_cost_rupees": 63780,
              "development_cost_rupees": 0,
              "current_value_rupees": 315000
            },
            {
              "location": "Kechchinabandi (v), H.B. Halli Tq",
              "sy_no": "194A/1",
              "total_area_acres": 6.28,
              "built_up_area": null,
              "inherited": false,
              "purchase_date": "2015-11-09",
              "purchase_cost_rupees": 636365,
              "development_cost_rupees": 0,
              "current_value_rupees": 3140000
            }
          ],
          "huf_details": [
            {
              "location": "Obulapuram (v)",
              "sy_no": "94B & 95A, 96B",
              "total_area_acres": 6.60,
              "built_up_area": null,
              "inherited": false,
              "purchase_date": "2000-05-05",
              "purchase_cost_rupees": 37011,
              "development_cost_rupees": 0,
              "current_value_rupees": 1650000
            },
            {
              "location": "Obulapuram (v)",
              "sy_no": "85 P",
              "total_area_acres": 16.06,
              "built_up_area": null,
              "inherited": false,
              "purchase_date": "2000-10-09",
              "purchase_cost_rupees": 72226,
              "development_cost_rupees": 0,
              "current_value_rupees": 4015000
            },
            {
              "location": "Obulapuram (v)",
              "sy_no": "93",
              "total_area_acres": 9.42,
              "built_up_area": null,
              "inherited": false,
              "purchase_date": "1999-06-30",
              "purchase_cost_rupees": 73895,
              "development_cost_rupees": 0,
              "current_value_rupees": 2355000
            },
            {
              "location": "Halkundi",
              "sy_no": "385",
              "total_area_acres": 4.28,
              "built_up_area": null,
              "inherited": false,
              "purchase_date": "2000-11-23",
              "purchase_cost_rupees": 122800,
              "development_cost_rupees": 0,
              "current_value_rupees": 642000
            },
            {
              "location": "Mincheri (v)",
              "sy_no": "26",
              "total_area_acres": 15.10,
              "built_up_area": null,
              "inherited": false,
              "purchase_date": "2008-01-18",
              "purchase_cost_rupees": 333820,
              "development_cost_rupees": 0,
              "current_value_rupees": 1520000
            }
          ]
        },
        {
          "sr_no": "ii",
          "description": "Non Agricultural Land",
          "self_value_rupees": 557600000,
          "spouse_value_rupees": 7200000,
          "huf_value_rupees": 0,
          "dependent1_value_rupees": 0,
          "dependent2_value_rupees": 0,
          "dependent3_value_rupees": 0,
          "total_value_rupees": 564800000,
          "self_details": [
            {
              "location": "Kolagal (v)",
              "sy_no": "812/B & C",
              "total_area_acres": 3.83,
              "built_up_area": null,
              "inherited": false,
              "purchase_date": "2013-07-09",
              "purchase_cost_rupees": 1258010,
              "development_cost_rupees": 0,
              "current_value_rupees": 26600000
            },
            {
              "location": "Ballari",
              "sy_no": "710/6",
              "total_area_sqft": 2180,
              "built_up_area": null,
              "inherited": false,
              "purchase_date": "2010-01-27",
              "purchase_cost_rupees": 1325000,
              "development_cost_rupees": 0,
              "current_value_rupees": 2025000
            },
            {
              "location": "Ballari",
              "sy_no": "713/2",
              "total_area_sqft": 5610,
              "built_up_area": null,
              "inherited": false,
              "purchase_date": "1999-03-13",
              "purchase_cost_rupees": 558914,
              "development_cost_rupees": 0,
              "current_value_rupees": 5220000
            },
            {
              "location": "Ballari",
              "sy_no": "146/B",
              "total_area_acres": 4.02,
              "built_up_area": null,
              "inherited": false,
              "purchase_date": "2009-05-07",
              "purchase_cost_rupees": 303575,
              "development_cost_rupees": 0,
              "current_value_rupees": 8055000
            },
            {
              "location": "Huligi",
              "sy_no": "278/297",
              "total_area_acres": 1.57,
              "built_up_area": null,
              "inherited": false,
              "purchase_date": "2009-05-07",
              "purchase_cost_rupees": 119005,
              "development_cost_rupees": 0,
              "current_value_rupees": 3200000
            },
            {
              "location": "Munirabad",
              "sy_no": "222",
              "total_area_acres": 2.60,
              "built_up_area": null,
              "inherited": false,
              "purchase_date": "2009-05-07",
              "purchase_cost_rupees": 196220,
              "development_cost_rupees": 0,
              "current_value_rupees": 8700000
            },
            {
              "location": "Ballari",
              "sy_no": "710/7",
              "total_area_sqft": 3130,
              "built_up_area": null,
              "inherited": false,
              "purchase_date": "2015-02-09",
              "purchase_cost_rupees": 4768680,
              "development_cost_rupees": 0,
              "current_value_rupees": 5500000
            },
            {
              "location": "Khanapur (v)",
              "sy_no": "18/1",
              "total_area_sqft": 1100,
              "built_up_area": null,
              "inherited": false,
              "purchase_date": "2014-06-26",
              "purchase_cost_rupees": 1025000,
              "development_cost_rupees": 231000,
              "current_value_rupees": 1525000
            },
            {
              "location": "Munirabad",
              "sy_no": "223/223",
              "total_area_acres": 1.92,
              "built_up_area": null,
              "inherited": false,
              "purchase_date": "2014-04-11",
              "purchase_cost_rupees": 614945,
              "development_cost_rupees": 0,
              "current_value_rupees": 6500000
            },
            {
              "location": "Shetty Halli",
              "sy_no": "58/3",
              "total_area_acres": 0.80,
              "built_up_area": null,
              "inherited": false,
              "purchase_date": "2008-01-31",
              "purchase_cost_rupees": 2803158,
              "development_cost_rupees": 1989000,
              "current_value_rupees": 73500000
            },
            {
              "location": "Shetty Halli",
              "sy_no": "58/6",
              "total_area_acres": 2.37,
              "built_up_area": null,
              "inherited": false,
              "purchase_date": "2008-04-15",
              "purchase_cost_rupees": 8321300,
              "development_cost_rupees": 5890000,
              "current_value_rupees": 218000000
            },
            {
              "location": "Shetty Halli",
              "sy_no": "58/4",
              "total_area_acres": 1.87,
              "built_up_area": null,
              "inherited": false,
              "purchase_date": "2009-06-17",
              "purchase_cost_rupees": 6438352,
              "development_cost_rupees": 4650000,
              "current_value_rupees": 172000000
            },
            {
              "location": "Ballari",
              "sy_no": "144/2A,12,1A/1,144/2a,144/1a4,144a/2",
              "total_area_sqft": 17147,
              "built_up_area": null,
              "inherited": false,
              "purchase_date": "2022-08-04",
              "purchase_cost_rupees": 21938750,
              "development_cost_rupees": 0,
              "current_value_rupees": 22000000
            }
          ],
          "spouse_details": [
            {
              "location": "Ananthashay Anagudi",
              "sy_no": "96/B3/B1& B2&B3/C4/1",
              "total_area_sqft": 7200,
              "built_up_area": null,
              "inherited": false,
              "purchase_date": "2009-01-21",
              "purchase_cost_rupees": 266000,
              "development_cost_rupees": 0,
              "current_value_rupees": 7200000
            }
          ],
          "huf_details": []
        },
        {
          "sr_no": "iii",
          "description": "Commercial Buildings",
          "self_value_rupees": 32000000,
          "spouse_value_rupees": 0,
          "huf_value_rupees": 0,
          "dependent1_value_rupees": 0,
          "dependent2_value_rupees": 0,
          "dependent3_value_rupees": 0,
          "total_value_rupees": 32000000,
          "self_details": [
            {
              "location": "Ballari",
              "sy_no": "527",
              "total_area_sqft": 16500,
              "built_up_area_sqft": 2334,
              "inherited": false,
              "purchase_date": "2003-06-28",
              "purchase_cost_rupees": 2218000,
              "development_cost_rupees": 0,
              "current_value_rupees": 32000000
            }
          ],
          "spouse_details": "Nil",
          "huf_details": "Nil"
        },
        {
          "sr_no": "iv",
          "description": "Residential Buildings",
          "self_value_rupees": 34000000,
          "spouse_value_rupees": 0,
          "huf_value_rupees": 0,
          "dependent1_value_rupees": 0,
          "dependent2_value_rupees": 0,
          "dependent3_value_rupees": 0,
          "total_value_rupees": 34000000,
          "self_details": [
            {
              "location": "Binnamangala, Bangalore",
              "pid": "82-24-550",
              "total_area_sqft": 2440,
              "built_up_area_sqft": 1675,
              "inherited": false,
              "purchase_date": "2011-10-14",
              "purchase_cost_rupees": 26930585,
              "development_cost_rupees": 0,
              "current_value_rupees": 34000000
            }
          ],
          "spouse_details": "Nil",
          "huf_details": "Nil"
        },
        {
          "sr_no": "v",
          "description": "Others",
          "self_value_rupees": 0,
          "spouse_value_rupees": 0,
          "huf_value_rupees": 0,
          "dependent1_value_rupees": 0,
          "dependent2_value_rupees": 0,
          "dependent3_value_rupees": 0,
          "total_value_rupees": 0,
          "self_details": "Nil",
          "spouse_details": "Nil",
          "huf_details": "Nil"
        }
      ]
    },
    "liabilities": {
      "report_status": "No Problems in Reading Affidavit Information",
      "grand_total_of_liabilities_self_rupees": 191975368,
      "grand_total_of_liabilities_spouse_rupees": 151811000,
      "grand_total_of_liabilities_huf_rupees": 0,
      "grand_total_of_liabilities_dependent1_rupees": 0,
      "grand_total_of_liabilities_dependent2_rupees": 0,
      "grand_total_of_liabilities_dependent3_rupees": 0,
      "grand_total_of_liabilities_total_rupees": 343786368,
      "grand_total_of_all_govt_dues_self_rupees": 0,
      "grand_total_of_all_govt_dues_spouse_rupees": 0,
      "grand_total_of_all_govt_dues_huf_rupees": 0,
      "grand_total_of_all_govt_dues_dependent1_rupees": 0,
      "grand_total_of_all_govt_dues_dependent2_rupees": 0,
      "grand_total_of_all_govt_dues_dependent3_rupees": 0,
      "grand_total_of_all_govt_dues_total_rupees": 0,
      "any_other_liabilities_in_dispute": {
        "self_amount_rupees": 0,
        "spouse_amount_rupees": 0,
        "huf_amount_rupees": 0,
        "dependent1_amount_rupees": 0,
        "dependent2_amount_rupees": 0,
        "dependent3_amount_rupees": 0,
        "total_amount_rupees": 0,
        "details": null
      },
      "items": [
        {
          "sr_no": "i",
          "description": "Loans from Banks / FIs",
          "self_value_rupees": 4825875,
          "spouse_value_rupees": 1811000,
          "huf_value_rupees": 0,
          "dependent1_value_rupees": 0,
          "dependent2_value_rupees": 0,
          "dependent3_value_rupees": 0,
          "total_value_rupees": 6636875,
          "self_details": [
            {
              "bank": "HDFC Bank Ltd",
              "loan_type": "Car Loan",
              "amount_rupees": 4825875
            }
          ],
          "spouse_details": [
            {
              "bank": "Axis Bank Ltd",
              "loan_type": "Secured Loan",
              "amount_rupees": 1811000
            }
          ]
        },
        {
          "sr_no": null,
          "description": "Loans due to Individual / Entity",
          "self_value_rupees": 187149493,
          "spouse_value_rupees": 150000000,
          "huf_value_rupees": 0,
          "dependent1_value_rupees": 0,
          "dependent2_value_rupees": 0,
          "dependent3_value_rupees": 0,
          "total_value_rupees": 337149493,
          "self_details": [
            {
              "name": "Gurunath Balkushi",
              "amount_rupees": 131000
            },
            {
              "name": "Nakshatra Enterprises",
              "amount_rupees": 4780
            },
            {
              "name": "N. Sharath Reddy",
              "amount_rupees": 2704079
            },
            {
              "name": "N. Surayanarayana Reddy",
              "amount_rupees": 136092075
            },
            {
              "name": "N. Suvarna",
              "amount_rupees": 45785701
            },
            {
              "name": "Sree Raghavendra Enterprises",
              "amount_rupees": 1992588
            },
            {
              "name": "Anilkumar Halshety",
              "amount_rupees": 88000
            },
            {
              "name": "Janabai",
              "amount_rupees": 146270
            },
            {
              "name": "Rajshekhar",
              "amount_rupees": 205000
            }
          ],
          "spouse_details": [
            {
              "name": "N. Bharath Reddy (Personal Loan)",
              "amount_rupees": 150000000
            }
          ]
        },
        {
          "sr_no": null,
          "description": "Any other Liability",
          "self_value_rupees": 0,
          "spouse_value_rupees": 0,
          "huf_value_rupees": 0,
          "dependent1_value_rupees": 0,
          "dependent2_value_rupees": 0,
          "dependent3_value_rupees": 0,
          "total_value_rupees": 0,
          "self_details": "Nil",
          "spouse_details": "Nil"
        },
        {
          "sr_no": "ii",
          "description": "Dues to departments dealing with government accommodation",
          "self_value_rupees": 0,
          "spouse_value_rupees": 0,
          "huf_value_rupees": 0,
          "dependent1_value_rupees": 0,
          "dependent2_value_rupees": 0,
          "dependent3_value_rupees": 0,
          "total_value_rupees": 0,
          "self_details": "Nil",
          "spouse_details": "Nil"
        },
        {
          "sr_no": null,
          "description": "Dues to departments dealing with supply of water",
          "self_value_rupees": 0,
          "spouse_value_rupees": 0,
          "huf_value_rupees": 0,
          "dependent1_value_rupees": 0,
          "dependent2_value_rupees": 0,
          "dependent3_value_rupees": 0,
          "total_value_rupees": 0,
          "self_details": "Nil",
          "spouse_details": "Nil"
        },
        {
          "sr_no": null,
          "description": "Dues to departments dealing with supply of electricity",
          "self_value_rupees": 0,
          "spouse_value_rupees": 0,
          "huf_value_rupees": 0,
          "dependent1_value_rupees": 0,
          "dependent2_value_rupees": 0,
          "dependent3_value_rupees": 0,
          "total_value_rupees": 0,
          "self_details": "Nil",
          "spouse_details": "Nil"
        },
        {
          "sr_no": null,
          "description": "Dues to departments dealing with telephones",
          "self_value_rupees": 0,
          "spouse_value_rupees": 0,
          "huf_value_rupees": 0,
          "dependent1_value_rupees": 0,
          "dependent2_value_rupees": 0,
          "dependent3_value_rupees": 0,
          "total_value_rupees": 0,
          "self_details": "Nil",
          "spouse_details": "Nil"
        },
        {
          "sr_no": null,
          "description": "Dues to departments dealing with supply of transport",
          "self_value_rupees": 0,
          "spouse_value_rupees": 0,
          "huf_value_rupees": 0,
          "dependent1_value_rupees": 0,
          "dependent2_value_rupees": 0,
          "dependent3_value_rupees": 0,
          "total_value_rupees": 0,
          "self_details": "Nil",
          "spouse_details": "Nil"
        },
        {
          "sr_no": null,
          "description": "Income Tax Dues",
          "self_value_rupees": 0,
          "spouse_value_rupees": 0,
          "huf_value_rupees": 0,
          "dependent1_value_rupees": 0,
          "dependent2_value_rupees": 0,
          "dependent3_value_rupees": 0,
          "total_value_rupees": 0,
          "self_details": "Nil",
          "spouse_details": "Nil"
        },
        {
          "sr_no": null,
          "description": "Wealth Tax Dues",
          "self_value_rupees": 0,
          "spouse_value_rupees": 0,
          "huf_value_rupees": 0,
          "dependent1_value_rupees": 0,
          "dependent2_value_rupees": 0,
          "dependent3_value_rupees": 0,
          "total_value_rupees": 0,
          "self_details": "Nil",
          "spouse_details": "Nil"
        },
        {
          "sr_no": null,
          "description": "Service Tax Dues",
          "self_value_rupees": 0,
          "spouse_value_rupees": 0,
          "huf_value_rupees": 0,
          "dependent1_value_rupees": 0,
          "dependent2_value_rupees": 0,
          "dependent3_value_rupees": 0,
          "total_value_rupees": 0,
          "self_details": "Nil",
          "spouse_details": "Nil"
        },
        {
          "sr_no": null,
          "description": "Property Tax Dues",
          "self_value_rupees": 0,
          "spouse_value_rupees": 0,
          "huf_value_rupees": 0,
          "dependent1_value_rupees": 0,
          "dependent2_value_rupees": 0,
          "dependent3_value_rupees": 0,
          "total_value_rupees": 0,
          "self_details": "Nil",
          "spouse_details": "Nil"
        },
        {
          "sr_no": null,
          "description": "Sales Tax Dues",
          "self_value_rupees": 0,
          "spouse_value_rupees": 0,
          "huf_value_rupees": 0,
          "dependent1_value_rupees": 0,
          "dependent2_value_rupees": 0,
          "dependent3_value_rupees": 0,
          "total_value_rupees": 0,
          "self_details": "Nil",
          "spouse_details": "Nil"
        },
        {
          "sr_no": null,
          "description": "GST Dues",
          "self_value_rupees": 0,
          "spouse_value_rupees": 0,
          "huf_value_rupees": 0,
          "dependent1_value_rupees": 0,
          "dependent2_value_rupees": 0,
          "dependent3_value_rupees": 0,
          "total_value_rupees": 0,
          "self_details": "Nil",
          "spouse_details": "Nil"
        },
        {
          "sr_no": null,
          "description": "Any Other Dues",
          "self_value_rupees": 0,
          "spouse_value_rupees": 0,
          "huf_value_rupees": 0,
          "dependent1_value_rupees": 0,
          "dependent2_value_rupees": 0,
          "dependent3_value_rupees": 0,
          "total_value_rupees": 0,
          "self_details": "Nil",
          "spouse_details": "Nil"
        }
      ]
    },
    "profession_or_occupation": {
      "self": "Business & Agriculturist",
      "spouse": "Business, House Wife, Agriculturist"
    },
    "sources_of_income": {
      "self": "Business Income, Agricultural Income",
      "spouse": "Business, Agricultural Income",
      "dependent": "NA"
    },
    "contracts_with_government_and_public_companies": {
      "candidate": "NA",
      "spouse": "NA",
      "dependent": "NA",
      "huf_or_trust": "NA",
      "partnership_firms": "NA",
      "private_companies": "NA"
    }
  }
}