{
  "candidate_name": "RAJA VENKATAPPA NAIK",
  "party": "INC",
  "constituency": "SHORAPUR (ST)",
  "state": "Karnataka 2023",
  "status": "Winner",
  "affidavit_info": {
    "personal_details": {
      "s_o_d_o_w_o": "Late Rajakumar Naik",
      "age": 66,
      "voter_enrolled_in": {
        "constituency": "36 Shorapur (Karnataka)",
        "serial_no": 498,
        "part_no": 90
      },
      "self_profession": "Social Worker",
      "spouse_profession": "House wife"
    },
    "summary": {
      "criminal_cases_count": 6,
      "total_assets_in_rupees": 232952188,
      "total_liabilities_in_rupees": 7930000
    },
    "educational_details": {
      "category": "12th Pass",
      "details": "MBBS (Not Completed) from MR Medical College Gulbarga in 1981, PUC from Nuthana Vidyalaya Junior College Kulburgi in 1979"
    },
    "income_tax_details": {
      "report_status": "No Problems in Reading Affidavit Information",
      "returns": [
        {
          "relation_type": "self",
          "pan_given": true,
          "financial_year": "2021 - 2022",
          "total_income_shown_in_itr_rupees": 762780
        },
        {
          "relation_type": "self",
          "pan_given": true,
          "financial_year": "2020 - 2021",
          "total_income_shown_in_itr_rupees": 947190
        },
        {
          "relation_type": "self",
          "pan_given": true,
          "financial_year": "2019 - 2020",
          "total_income_shown_in_itr_rupees": 1119820
        },
        {
          "relation_type": "self",
          "pan_given": true,
          "financial_year": "2018 - 2019",
          "total_income_shown_in_itr_rupees": 829690
        },
        {
          "relation_type": "self",
          "pan_given": true,
          "financial_year": "2017 - 2018",
          "total_income_shown_in_itr_rupees": 820870
        },
        {
          "relation_type": "spouse",
          "pan_given": true,
          "financial_year": "2021 - 2022",
          "total_income_shown_in_itr_rupees": 485970
        },
        {
          "relation_type": "spouse",
          "pan_given": true,
          "financial_year": "2020 - 2021",
          "total_income_shown_in_itr_rupees": 301470
        },
        {
          "relation_type": "spouse",
          "pan_given": true,
          "financial_year": "2019 - 2020",
          "total_income_shown_in_itr_rupees": 287330
        },
        {
          "relation_type": "spouse",
          "pan_given": true,
          "financial_year": "2018 - 2019",
          "total_income_shown_in_itr_rupees": 610470
        },
        {
          "relation_type": "spouse",
          "pan_given": true,
          "financial_year": "2017 - 2018",
          "total_income_shown_in_itr_rupees": 672320
        },
        {
          "relation_type": "huf",
          "pan_given": true,
          "financial_year": "2018 - 2019",
          "total_income_shown_in_itr_rupees": 320000
        },
        {
          "relation_type": "huf",
          "pan_given": true,
          "financial_year": "2017 - 2018",
          "total_income_shown_in_itr_rupees": 339590
        },
        {
          "relation_type": "huf",
          "pan_given": true,
          "financial_year": null,
          "total_income_shown_in_itr_rupees": 0
        },
        {
          "relation_type": "huf",
          "pan_given": true,
          "financial_year": null,
          "total_income_shown_in_itr_rupees": 0
        },
        {
          "relation_type": "huf",
          "pan_given": true,
          "financial_year": null,
          "total_income_shown_in_itr_rupees": 0
        },
        {
          "relation_type": "dependent1",
          "pan_given": true,
          "financial_year": "2020 - 2021",
          "total_income_shown_in_itr_rupees": 4050
        },
        {
          "relation_type": "dependent1",
          "pan_given": true,
          "financial_year": null,
          "total_income_shown_in_itr_rupees": 0
        },
        {
          "relation_type": "dependent1",
          "pan_given": true,
          "financial_year": null,
          "total_income_shown_in_itr_rupees": 0
        },
        {
          "relation_type": "dependent1",
          "pan_given": true,
          "financial_year": null,
          "total_income_shown_in_itr_rupees": 0
        },
        {
          "relation_type": "dependent1",
          "pan_given": true,
          "financial_year": null,
          "total_income_shown_in_itr_rupees": 0
        },
        {
          "relation_type": "dependent2",
          "pan_given": false,
          "financial_year": null,
          "total_income_shown_in_itr_rupees": 0
        },
        {
          "relation_type": "dependent2",
          "pan_given": false,
          "financial_year": null,
          "total_income_shown_in_itr_rupees": 0
        },
        {
          "relation_type": "dependent2",
          "pan_given": false,
          "financial_year": null,
          "total_income_shown_in_itr_rupees": 0
        },
        {
          "relation_type": "dependent2",
          "pan_given": false,
          "financial_year": null,
          "total_income_shown_in_itr_rupees": 0
        },
        {
          "relation_type": "dependent2",
          "pan_given": false,
          "financial_year": null,
          "total_income_shown_in_itr_rupees": 0
        },
        {
          "relation_type": "dependent3",
          "pan_given": false,
          "financial_year": null,
          "total_income_shown_in_itr_rupees": 0
        },
        {
          "relation_type": "dependent3",
          "pan_given": false,
          "financial_year": null,
          "total_income_shown_in_itr_rupees": 0
        },
        {
          "relation_type": "dependent3",
          "pan_given": false,
          "financial_year": null,
          "total_income_shown_in_itr_rupees": 0
        },
        {
          "relation_type": "dependent3",
          "pan_given": false,
          "financial_year": null,
          "total_income_shown_in_itr_rupees": 0
        },
        {
          "relation_type": "dependent3",
          "pan_given": false,
          "financial_year": null,
          "total_income_shown_in_itr_rupees": 0
        }
      ]
    },
    "criminal_cases": {
      "report_status": "No Problems in Reading Affidavit Information",
      "brief_details_ipc_bns": [
        {
          "charges_related_to": "Punishment for criminal intimidation",
          "ipc_section": "506",
          "count": 3
        },
        {
          "charges_related_to": "Voluntarily causing hurt by dangerous weapons or means",
          "ipc_section": "324",
          "count": 2
        },
        {
          "charges_related_to": "Voluntarily causing grievous hurt by dangerous weapons or means",
          "ipc_section": "326",
          "count": 1
        },
        {
          "charges_related_to": "Every member of unlawful assembly guilty of offence committed in prosecution of common object",
          "ipc_section": "149",
          "count": 3
        },
        {
          "charges_related_to": "Punishment for Being member of an unlawful assembly",
          "ipc_section": "143",
          "count": 3
        },
        {
          "charges_related_to": "Punishment for Rioting",
          "ipc_section": "147",
          "count": 3
        },
        {
          "charges_related_to": "Intentional insult with intent to provoke breach of the peace",
          "ipc_section": "504",
          "count": 3
        },
        {
          "charges_related_to": "Rioting, armed with deadly weapon",
          "ipc_section": "148",
          "count": 2
        },
        {
          "charges_related_to": "Assaulting or obstructing public servant when suppressing riot, etc.",
          "ipc_section": "152",
          "count": 1
        },
        {
          "charges_related_to": "Mischief causing damage to the amount of fifty rupees",
          "ipc_section": "427",
          "count": 1
        },
        {
          "charges_related_to": "Abettor present when offence is committed",
          "ipc_section": "114",
          "count": 1
        },
        {
          "charges_related_to": "Punishment for voluntarily causing hurt",
          "ipc_section": "323",
          "count": 1
        },
        {
          "charges_related_to": "Disobedience to order duly promulgated by public servant",
          "ipc_section": "188",
          "count": 1
        },
        {
          "charges_related_to": "Assault or criminal force to deter public servant from discharge of his duty",
          "ipc_section": "353",
          "count": 1
        },
        {
          "charges_related_to": "Threat of injury to public servant",
          "ipc_section": "189",
          "count": 1
        },
        {
          "charges_related_to": "Wantonly giving provocation with intent to cause riot-if rioting be committed-if not committed",
          "ipc_section": "153",
          "count": 1
        }
      ],
      "pending_cases": [
        {
          "serial_no": 1,
          "fir_no": "10/2016, Hunasagi Police Station, Tq- Hunasagi Dist: Yadagiri",
          "case_no": "378/2016",
          "court": "ADDL JMFC, Court at Shorapur",
          "ipc_sections_applicable": "188",
          "other_details_or_acts_sections_applicable": null,
          "charges_framed": true,
          "date_on_which_charges_were_framed": "2016-05-02",
          "appeal_filed": false,
          "details_and_present_status_of_appeal": null
        },
        {
          "serial_no": 2,
          "fir_no": "344/2018, Shorapur Police Station, Tq- Shorapur Dist: Yadagiri",
          "case_no": "474/2019",
          "court": "PRL JMFC, Court at Shorapur",
          "ipc_sections_applicable": "143, 147, 189, 353, 504, 506, 149",
          "other_details_or_acts_sections_applicable": null,
          "charges_framed": true,
          "date_on_which_charges_were_framed": "2019-04-09",
          "appeal_filed": false,
          "details_and_present_status_of_appeal": null
        },
        {
          "serial_no": 3,
          "fir_no": "29/2023, Kodekal Police Station, Tq: Hunasagi, Dist: Yadagiri",
          "case_no": null,
          "court": "ADDL JMFC, Court Shorapur",
          "ipc_sections_applicable": "143, 147, 148, 323, 324, 326, 504, 506, 149",
          "other_details_or_acts_sections_applicable": null,
          "charges_framed": false,
          "date_on_which_charges_were_framed": null,
          "appeal_filed": false,
          "details_and_present_status_of_appeal": null
        },
        {
          "serial_no": 4,
          "fir_no": "24/2023, Kodekal Police Station, Tq: Hunasagi, Dist: Yadagiri",
          "case_no": null,
          "court": "ADDL JMFC, Court Shorapur",
          "ipc_sections_applicable": "143, 147, 148, 114, 324, 427, 504, 506, 149",
          "other_details_or_acts_sections_applicable": null,
          "charges_framed": false,
          "date_on_which_charges_were_framed": null,
          "appeal_filed": false,
          "details_and_present_status_of_appeal": null
        },
        {
          "serial_no": 5,
          "fir_no": "27/2023, Kodekal Police Station, Tq: Hunasagi, Dist: Yadagiri",
          "case_no": null,
          "court": "ADDL JMFC, Court Shorapur",
          "ipc_sections_applicable": "152",
          "other_details_or_acts_sections_applicable": null,
          "charges_framed": false,
          "date_on_which_charges_were_framed": null,
          "appeal_filed": false,
          "details_and_present_status_of_appeal": null
        },
        {
          "serial_no": 6,
          "fir_no": "63/2022, Shorapur Police Station, Tq: Shorapur, Dist: Yadagiri",
          "case_no": "2183/2022",
          "court": "PRL JMFC, Court at Shorapur",
          "ipc_sections_applicable": "153",
          "other_details_or_acts_sections_applicable": null,
          "charges_framed": true,
          "date_on_which_charges_were_framed": "2022-07-18",
          "appeal_filed": false,
          "details_and_present_status_of_appeal": null
        }
      ],
      "convicted_cases": []
    },
    "movable_assets": {
      "report_status": "No Problems in Reading Affidavit Information",
      "gross_total_value_self_rupees": 21884460,
      "gross_total_value_spouse_rupees": 15335023,
      "gross_total_value_huf_rupees": 5743224,
      "gross_total_value_dependent1_rupees": 6977214,
      "gross_total_value_dependent2_rupees": 0,
      "gross_total_value_dependent3_rupees": 0,
      "gross_total_value_total_rupees": 49939921,
      "items": [
        {
          "sr_no": "i",
          "description": "Cash",
          "self_value_rupees": 650000,
          "spouse_value_rupees": 425000,
          "huf_value_rupees": 215000,
          "dependent1_value_rupees": 365000,
          "dependent2_value_rupees": 0,
          "dependent3_value_rupees": 0,
          "total_value_rupees": 1655000
        },
        {
          "sr_no": "ii",
          "description": "Deposits in Banks, Financial Institutions and Non-Banking Financial Companies",
          "self_value_rupees": 5396860,
          "spouse_value_rupees": 2901996,
          "huf_value_rupees": 227424,
          "dependent1_value_rupees": 137762,
          "dependent2_value_rupees": 0,
          "dependent3_value_rupees": 0,
          "total_value_rupees": 7997442,
          "self_details": [
            "Karnataka State Co-operative Apex Bank Ltd, Legislator Home Branch, SB No 102610201000xxxxx 11,23,083",
            "Canara Bank, Shorapur Branch, SB No 140611600xxxxx 53,765",
            "Karnataka Bank, Shorapur Branch, SB No 713250010044xxxxx 42,53,412"
          ],
          "spouse_details": [
            "Canara Bank, Vijayanagar Branch, SB No 114610103xxxxx 7,62,325",
            "Canara Bank, Shorapur Branch, SB No 140610100xxxxx 3,17,577",
            "Karnataka Bank, Shorapur Branch, No 713250010138xxxxx 11,22,094"
          ],
          "huf_details": "State Bank of India, RPC Layout Branch, SB No 1056274xxxxx 2,27,424",
          "dependent1_details": [
            "Canara Bank, Vijayanagar, SB No 114610192xxxxx 2,260",
            "State Bank of India, Kakkera Branch, SB No 3453805xxxxx 134",
            "Karnataka Bank, Vijayanagar, SB No 105250011177xxxxx 1,01,050",
            "Karnataka Bank, Shorapur, SB No 713250010181xxxxx 34,318"
          ]
        },
        {
          "sr_no": "iii",
          "description": "Bonds, Debentures and Shares in companies",
          "self_value_rupees": 0,
          "spouse_value_rupees": 0,
          "huf_value_rupees": 0,
          "dependent1_value_rupees": 0,
          "dependent2_value_rupees": 0,
          "dependent3_value_rupees": 0,
          "total_value_rupees": 0
        },
        {
          "sr_no": "iv",
          "description": "(a) NSS, Postal Savings etc",
          "self_value_rupees": 0,
          "spouse_value_rupees": 1122227,
          "huf_value_rupees": 0,
          "dependent1_value_rupees": 0,
          "dependent2_value_rupees": 0,
          "dependent3_value_rupees": 0,
          "total_value_rupees": 1122227,
          "spouse_details": "Post Office- Vijayanagar Branch, No 334390xxxxx 11,22,227"
        },
        {
          "sr_no": null,
          "description": "(b) LIC or other insurance Policies",
          "self_value_rupees": 0,
          "spouse_value_rupees": 0,
          "huf_value_rupees": 0,
          "dependent1_value_rupees": 0,
          "dependent2_value_rupees": 0,
          "dependent3_value_rupees": 0,
          "total_value_rupees": 0
        },
        {
          "sr_no": "v",
          "description": "Personal loans/advance given",
          "self_value_rupees": 16430000,
          "spouse_value_rupees": 0,
          "huf_value_rupees": 4030000,
          "dependent1_value_rupees": 0,
          "dependent2_value_rupees": 0,
          "dependent3_value_rupees": 0,
          "total_value_rupees": 16430000,
          "self_details": [
            "Lata Venkatappa Naik  7,00,000",
            "Mohmad Toufiq 5,00,000",
            "Shivraj 5,00,000",
            "Mrs. Jayashree 5,00,000",
            "Hanamanta 5,00,000",
            "Venkatesh 5,00,000",
            "Husainpasha 5,00,000",
            "Mounesh 5,00,000",
            "Hanumantraya Tammanna 5,00,000",
            "Adiveppa Telkar 5,00,000",
            "Venkanna 5,00,000",
            "Hussaina Be W O Hussena P 5,00,000",
            "R M Kulkarni 10,00,000",
            "N A Inmadar 10,00,000",
            "Vasu Automobiles 42,00,000"
          ],
          "huf_details": [
            "Lata Venkatappa Naik 20,30,000",
            "Vasu Automobiles 20,00,000"
          ]
        },
        {
          "sr_no": "vi",
          "description": "Motor Vehicles (details of make, etc.)",
          "self_value_rupees": 2315000,
          "spouse_value_rupees": 0,
          "huf_value_rupees": 0,
          "dependent1_value_rupees": 2428852,
          "dependent2_value_rupees": 0,
          "dependent3_value_rupees": 0,
          "total_value_rupees": 4743852,
          "self_details": [
            "Fortuner Toyota, KA04MM3334, Year- 2013 23,00,000",
            "Passion- Hero Honda, KA33J361, Year- 2010 15,000"
          ],
          "dependent1_details": [
            "GTR250RN- Hyosung KA03HW4006, Year- 2014 75,000",
            "Alcazar, Hyundai Motor, KA02MR6392, Year- 2021 23,53,852"
          ]
        },
        {
          "sr_no": "vii",
          "description": "Jewellery (give details weight value)",
          "self_value_rupees": 1089200,
          "spouse_value_rupees": 11635800,
          "huf_value_rupees": 1270800,
          "dependent1_value_rupees": 4045600,
          "dependent2_value_rupees": 0,
          "dependent3_value_rupees": 0,
          "total_value_rupees": 17991400,
          "self_details": "175 Gram 10,89,200",
          "spouse_details": [
            "Jewelries- 1700 gram 1,05,80,800",
            "Silver- 12.50 Kg 10,05,000"
          ],
          "huf_details": [
            "Jewelries- 750 gram  4,66,800",
            "Silver- 10 Kg 8,04,000"
          ],
          "dependent1_details": "Jewelries- 650 gram  40,45,600"
        },
        {
          "sr_no": "viii",
          "description": "Other assets, such as values of claims / interests",
          "self_value_rupees": 0,
          "spouse_value_rupees": 0,
          "huf_value_rupees": 0,
          "dependent1_value_rupees": 0,
          "dependent2_value_rupees": 0,
          "dependent3_value_rupees": 0,
          "total_value_rupees": 0
        }
      ]
    },
    "immovable_assets": {
      "report_status": "No Problems in Reading Affidavit Information",
      "total_current_market_value_self_rupees": 105033427,
      "total_current_market_value_spouse_rupees": 70052293,
      "total_current_market_value_huf_rupees": 1567500,
      "total_current_market_value_dependent1_rupees": 6359047,
      "total_current_market_value_dependent2_rupees": 0,
      "total_current_market_value_dependent3_rupees": 0,
      "total_current_market_value_total_rupees": 183012267,
      "items": [
        {
          "sr_no": "i",
          "description": "Agricultural Land",
          "self_value_rupees": 92452895,
          "spouse_value_rupees": 0,
          "huf_value_rupees": 11087500,
          "dependent1_value_rupees": 39441220,
          "dependent2_value_rupees": 0,
          "dependent3_value_rupees": 0,
          "total_value_rupees": 92452895,
          "self_details": [
            {
              "location": "Shorapur",
              "sy_no": "30/1A",
              "total_area": "5 Acre 32 Guntas",
              "inherited": true,
              "purchase_date": "0000-00-00",
              "purchase_cost_rupees": 0,
              "development_cost_rupees": 0,
              "current_value_rupees": 3625000
            },
            {
              "location": "Jalibenchi Shorapur",
              "sy_no": "84",
              "total_area": "18 Acres",
              "inherited": true,
              "purchase_date": "0000-00-00",
              "purchase_cost_rupees": 0,
              "development_cost_rupees": 0,
              "current_value_rupees": 4500000
            },
            {
              "location": "Jalibenchi Shorapur",
              "sy_no": "19",
              "total_area": "1 Acre 11 Guntas",
              "inherited": true,
              "purchase_date": "0000-00-00",
              "purchase_cost_rupees": 0,
              "development_cost_rupees": 0,
              "current_value_rupees": 318750
            },
            {
              "location": "Jalibenchi Shorapur",
              "sy_no": "24",
              "total_area": "8 Acre",
              "inherited": true,
              "purchase_date": "0000-00-00",
              "purchase_cost_rupees": 0,
              "development_cost_rupees": 0,
              "current_value_rupees": 2000000
            },
            {
              "location": "Jalibenchi Shorapur",
              "sy_no": "44",
              "total_area": "31 Acres 2 Guntas",
              "inherited": true,
              "purchase_date": "0000-00-00",
              "purchase_cost_rupees": 0,
              "development_cost_rupees": 0,
              "current_value_rupees": 7762500
            },
            {
              "location": "Jalibenchi Shorapur",
              "sy_no": "46",
              "total_area": "4 Acres 1 Guntas",
              "inherited": true,
              "purchase_date": "0000-00-00",
              "purchase_cost_rupees": 0,
              "development_cost_rupees": 0,
              "current_value_rupees": 1006250
            },
            {
              "location": "Malagatti Village, Joint Property",
              "sy_no": "181/A",
              "total_area": "3 Acres 17 Guntas",
              "inherited": false,
              "purchase_date": "2002-11-14",
              "purchase_cost_rupees": 139390,
              "development_cost_rupees": 0,
              "current_value_rupees": 822000
            },
            {
              "location": "Malagatti Village, Joint Property",
              "sy_no": "179",
              "total_area": "6 Acres 19 Guntas",
              "inherited": false,
              "purchase_date": "2011-09-23",
              "purchase_cost_rupees": 0,
              "development_cost_rupees": 0,
              "current_value_rupees": 1554000
            },
            {
              "location": "Jalibenchi Shorapur",
              "sy_no": "56",
              "total_area": "148 Acres 30 Guntas",
              "inherited": true,
              "purchase_date": "0000-00-00",
              "purchase_cost_rupees": 0,
              "development_cost_rupees": 0,
              "current_value_rupees": 37187500
            },
            {
              "location": "Jalibenchi Shorapur",
              "sy_no": "78",
              "total_area": "37.5 Guntas",
              "inherited": true,
              "purchase_date": "0000-00-00",
              "purchase_cost_rupees": 0,
              "development_cost_rupees": 0,
              "current_value_rupees": 234375
            },
            {
              "location": "Jalibenchi Shorapur",
              "sy_no": "67",
              "total_area": "13 Acres 19 Guntas",
              "inherited": true,
              "purchase_date": "0000-00-00",
              "purchase_cost_rupees": 0,
              "development_cost_rupees": 0,
              "current_value_rupees": 3368750
            },
            {
              "location": "Jalibenchi Shorapur",
              "sy_no": "76",
              "total_area": "8 Acres 15 Guntas",
              "inherited": true,
              "purchase_date": "0000-00-00",
              "purchase_cost_rupees": 0,
              "development_cost_rupees": 0,
              "current_value_rupees": 2093750
            },
            {
              "location": "Jalibenchi Shorapur",
              "sy_no": "77",
              "total_area": "6 Acres",
              "inherited": true,
              "purchase_date": "0000-00-00",
              "purchase_cost_rupees": 0,
              "development_cost_rupees": 0,
              "current_value_rupees": 1500000
            },
            {
              "location": "Jalibenchi Shorapur",
              "sy_no": "354/1-1",
              "total_area": "41 Acres 16 Guntas",
              "inherited": true,
              "purchase_date": "0000-00-00",
              "purchase_cost_rupees": 0,
              "development_cost_rupees": 0,
              "current_value_rupees": 10350000
            },
            {
              "location": "Khanapura Shorapur",
              "sy_no": "116/1/3",
              "total_area": "6 Acres",
              "inherited": false,
              "purchase_date": "2016-04-28",
              "purchase_cost_rupees": 3253645,
              "development_cost_rupees": 0,
              "current_value_rupees": 3660000
            },
            {
              "location": "Khanapura Shorapur",
              "sy_no": "116/2",
              "total_area": "4 Acres 36 Guntas",
              "inherited": false,
              "purchase_date": "2016-04-28",
              "purchase_cost_rupees": 2711605,
              "development_cost_rupees": 0,
              "current_value_rupees": 2989000
            },
            {
              "location": "Arekere Shorapur",
              "sy_no": "39/1",
              "total_area": "13 Acres 4 Guntas",
              "inherited": false,
              "purchase_date": "2015-10-06",
              "purchase_cost_rupees": 2614015,
              "development_cost_rupees": 0,
              "current_value_rupees": 3969300
            }
          ],
          "huf_details": [
            {
              "location": "Malagatti Village, Shorapur",
              "sy_no": "176/2",
              "total_area": "2 ACres",
              "inherited": false,
              "purchase_date": "2014-11-27",
              "purchase_cost_rupees": 288480,
              "development_cost_rupees": 0,
              "current_value_rupees": 480000
            },
            {
              "location": "Malagatti Village, Shorapur",
              "sy_no": "176/3",
              "total_area": "2 Acres 20 Guntas",
              "inherited": false,
              "purchase_date": "2014-11-27",
              "purchase_cost_rupees": 361160,
              "development_cost_rupees": 0,
              "current_value_rupees": 600000
            },
            {
              "location": "Vanakiyal",
              "sy_no": "94/7",
              "total_area": "25 Guntas",
              "inherited": false,
              "purchase_date": "2015-12-10",
              "purchase_cost_rupees": 144560,
              "development_cost_rupees": 0,
              "current_value_rupees": 487500
            }
          ],
          "dependent1_details": [
            {
              "location": "Malagati Village, Joint Property",
              "sy_no": "179",
              "total_area": "10 Acres 17 Guntas",
              "inherited": false,
              "purchase_date": "2006-09-25",
              "purchase_cost_rupees": 499695,
              "development_cost_rupees": 0,
              "current_value_rupees": 2502000
            },
            {
              "location": "Malagatti Village, Joint Property",
              "sy_no": "181/A",
              "total_area": "3 Acres 17 Guntas",
              "inherited": false,
              "purchase_date": "2002-11-14",
              "purchase_cost_rupees": 139390,
              "development_cost_rupees": 0,
              "current_value_rupees": 822000
            },
            {
              "location": "Malagatti Village",
              "sy_no": "176/4",
              "total_area": "15 Guntas",
              "inherited": false,
              "purchase_date": "2021-01-19",
              "purchase_cost_rupees": 107380,
              "development_cost_rupees": 0,
              "current_value_rupees": 107380
            },
            {
              "location": "Malagatti Village",
              "sy_no": "176/5",
              "total_area": "2 Acres",
              "inherited": false,
              "purchase_date": "2021-01-19",
              "purchase_cost_rupees": 512840,
              "development_cost_rupees": 0,
              "current_value_rupees": 512840
            }
          ]
        },
        {
          "sr_no": "ii",
          "description": "Non Agricultural Land",
          "self_value_rupees": 0,
          "spouse_value_rupees": 29050279,
          "huf_value_rupees": 0,
          "dependent1_value_rupees": 400000,
          "dependent2_value_rupees": 0,
          "dependent3_value_rupees": 0,
          "total_value_rupees": 29450279,
          "spouse_details": {
            "location": "Lottegollahalli Jakkur",
            "sy_no": "98/1/2/3",
            "total_area": "2400 sq ft",
            "inherited": false,
            "purchase_date": "1997-02-20",
            "purchase_cost_rupees": 56974,
            "development_cost_rupees": 0,
            "current_value_rupees": 29050279
          },
          "dependent1_details": {
            "location": "Hunsagi- Joint Property",
            "old_no": "17-80",
            "new_no": "16-150",
            "total_area": "325 sq ft",
            "inherited": false,
            "purchase_date": "2003-05-24",
            "purchase_cost_rupees": 4500,
            "development_cost_rupees": 0,
            "current_value_rupees": 400000
          }
        },
        {
          "sr_no": "iii",
          "description": "Commercial Buildings",
          "self_value_rupees": 0,
          "spouse_value_rupees": 0,
          "huf_value_rupees": 0,
          "dependent1_value_rupees": 0,
          "dependent2_value_rupees": 0,
          "dependent3_value_rupees": 0,
          "total_value_rupees": 0
        },
        {
          "sr_no": "iv",
          "description": "Residential Buildings",
          "self_value_rupees": 18092252,
          "spouse_value_rupees": 40999235,
          "huf_value_rupees": 0,
          "dependent1_value_rupees": 2014827,
          "dependent2_value_rupees": 0,
          "dependent3_value_rupees": 0,
          "total_value_rupees": 61109093,
          "self_details": [
            {
              "location": "Mulla Mauhalla, Shoprapur",
              "sy_no": "7-2-78",
              "total_area": "9750 sq ft",
              "built_up_area": "4199 sq ft",
              "inherited": false,
              "purchase_date": "2017-04-27",
              "purchase_cost_rupees": 3070810,
              "development_cost_rupees": 0,
              "current_value_rupees": 3100000
            },
            {
              "location": "Hampinagar Vijayanagar, Bangalore",
              "sy_no": "201",
              "total_area": "534 sq ft",
              "inherited": false,
              "purchase_date": "2017-06-06",
              "purchase_cost_rupees": 12464762,
              "development_cost_rupees": 828660,
              "current_value_rupees": 14992252
            }
          ],
          "spouse_details": [
            {
              "location": "Hampinagar, Vijayanagar, Bangalore",
              "sy_no": "202",
              "total_area": "330 sq ft",
              "built_up_area": "1236 sq ft",
              "inherited": false,
              "purchase_date": "2017-10-06",
              "purchase_cost_rupees": 7819707,
              "development_cost_rupees": 0,
              "current_value_rupees": 9283779
            },
            {
              "location": "Vijayanagar Bangalore",
              "sy_no": "3445/A",
              "total_area": "2400 sq ft",
              "built_up_area": "3460 sq ft",
              "inherited": false,
              "purchase_date": "1997-07-02",
              "purchase_cost_rupees": 1700000,
              "development_cost_rupees": 5000000,
              "current_value_rupees": 31718235
            }
          ],
          "dependent1_details": {
            "location": "Uddar Oni, Shorapur",
            "sy_no": "7-0-95-02-75",
            "total_area": "2995 sq ft",
            "built_up_area": "2995 sq ft",
            "inherited": false,
            "purchase_date": "2002-02-14",
            "purchase_cost_rupees": 100078,
            "development_cost_rupees": 250000,
            "current_value_rupees": 2014827
          }
        },
        {
          "sr_no": "v",
          "description": "Others",
          "self_value_rupees": 0,
          "spouse_value_rupees": 0,
          "huf_value_rupees": 0,
          "dependent1_value_rupees": 0,
          "dependent2_value_rupees": 0,
          "dependent3_value_rupees": 0,
          "total_value_rupees": 0
        }
      ]
    },
    "liabilities": {
      "report_status": "No Problems in Reading Affidavit Information",
      "grand_total_of_liabilities_self_rupees": 5200000,
      "grand_total_of_liabilities_spouse_rupees": 2730000,
      "grand_total_of_liabilities_huf_rupees": 0,
      "grand_total_of_liabilities_dependent1_rupees": 0,
      "grand_total_of_liabilities_dependent2_rupees": 0,
      "grand_total_of_liabilities_dependent3_rupees": 0,
      "grand_total_of_liabilities_total_rupees": 7930000,
      "grand_total_of_all_govt_dues_self_rupees": 0,
      "grand_total_of_all_govt_dues_spouse_rupees": 0,
      "grand_total_of_all_govt_dues_huf_rupees": 0,
      "grand_total_of_all_govt_dues_dependent1_rupees": 0,
      "grand_total_of_all_govt_dues_dependent2_rupees": 0,
      "grand_total_of_all_govt_dues_dependent3_rupees": 0,
      "grand_total_of_all_govt_dues_total_rupees": 0,
      "any_other_liabilities_in_dispute": {
        "self_amount_rupees": 0,
        "spouse_amount_rupees": 0,
        "huf_amount_rupees": 0,
        "dependent1_amount_rupees": 0,
        "dependent2_amount_rupees": 0,
        "dependent3_amount_rupees": 0,
        "total_amount_rupees": 0,
        "details": []
      },
      "items": [
        {
          "sr_no": "i",
          "description": "Loans from Banks / FIs",
          "self_value_rupees": 0,
          "spouse_value_rupees": 0,
          "huf_value_rupees": 0,
          "dependent1_value_rupees": 0,
          "dependent2_value_rupees": 0,
          "dependent3_value_rupees": 0,
          "total_value_rupees": 0
        },
        {
          "sr_no": null,
          "description": "Loans due to Individual / Entity",
          "self_value_rupees": 5200000,
          "spouse_value_rupees": 2730000,
          "huf_value_rupees": 0,
          "dependent1_value_rupees": 0,
          "dependent2_value_rupees": 0,
          "dependent3_value_rupees": 0,
          "total_value_rupees": 7930000,
          "self_details": {
            "name": "Vitthal Yadav",
            "loan_type": "Unsecured Loan",
            "amount_rupees": 5200000
          },
          "spouse_details": [
            {
              "name": "Raja Venkatappa Naik",
              "amount_rupees": 700000
            },
            {
              "name": "Raja Venkatappa Naik HUF",
              "amount_rupees": 2030000
            }
          ]
        },
        {
          "sr_no": null,
          "description": "Any other Liability",
          "self_value_rupees": 0,
          "spouse_value_rupees": 0,
          "huf_value_rupees": 0,
          "dependent1_value_rupees": 0,
          "dependent2_value_rupees": 0,
          "dependent3_value_rupees": 0,
          "total_value_rupees": 0
        },
        {
          "sr_no": "ii",
          "description": "Dues to departments dealing with government accommodation",
          "self_value_rupees": 0,
          "spouse_value_rupees": 0,
          "huf_value_rupees": 0,
          "dependent1_value_rupees": 0,
          "dependent2_value_rupees": 0,
          "dependent3_value_rupees": 0,
          "total_value_rupees": 0
        },
        {
          "sr_no": null,
          "description": "Dues to departments dealing with supply of water",
          "self_value_rupees": 0,
          "spouse_value_rupees": 0,
          "huf_value_rupees": 0,
          "dependent1_value_rupees": 0,
          "dependent2_value_rupees": 0,
          "dependent3_value_rupees": 0,
          "total_value_rupees": 0
        },
        {
          "sr_no": null,
          "description": "Dues to departments dealing with supply of electricity",
          "self_value_rupees": 0,
          "spouse_value_rupees": 0,
          "huf_value_rupees": 0,
          "dependent1_value_rupees": 0,
          "dependent2_value_rupees": 0,
          "dependent3_value_rupees": 0,
          "total_value_rupees": 0
        },
        {
          "sr_no": null,
          "description": "Dues to departments dealing with telephones",
          "self_value_rupees": 0,
          "spouse_value_rupees": 0,
          "huf_value_rupees": 0,
          "dependent1_value_rupees": 0,
          "dependent2_value_rupees": 0,
          "dependent3_value_rupees": 0,
          "total_value_rupees": 0
        },
        {
          "sr_no": null,
          "description": "Dues to departments dealing with supply of transport",
          "self_value_rupees": 0,
          "spouse_value_rupees": 0,
          "huf_value_rupees": 0,
          "dependent1_value_rupees": 0,
          "dependent2_value_rupees": 0,
          "dependent3_value_rupees": 0,
          "total_value_rupees": 0
        },
        {
          "sr_no": null,
          "description": "Income Tax Dues",
          "self_value_rupees": 0,
          "spouse_value_rupees": 0,
          "huf_value_rupees": 0,
          "dependent1_value_rupees": 0,
          "dependent2_value_rupees": 0,
          "dependent3_value_rupees": 0,
          "total_value_rupees": 0
        },
        {
          "sr_no": null,
          "description": "Wealth Tax Dues",
          "self_value_rupees": 0,
          "spouse_value_rupees": 0,
          "huf_value_rupees": 0,
          "dependent1_value_rupees": 0,
          "dependent2_value_rupees": 0,
          "dependent3_value_rupees": 0,
          "total_value_rupees": 0
        },
        {
          "sr_no": null,
          "description": "Service Tax Dues",
          "self_value_rupees": 0,
          "spouse_value_rupees": 0,
          "huf_value_rupees": 0,
          "dependent1_value_rupees": 0,
          "dependent2_value_rupees": 0,
          "dependent3_value_rupees": 0,
          "total_value_rupees": 0
        },
        {
          "sr_no": null,
          "description": "Property Tax Dues",
          "self_value_rupees": 0,
          "spouse_value_rupees": 0,
          "huf_value_rupees": 0,
          "dependent1_value_rupees": 0,
          "dependent2_value_rupees": 0,
          "dependent3_value_rupees": 0,
          "total_value_rupees": 0
        },
        {
          "sr_no": null,
          "description": "Sales Tax Dues",
          "self_value_rupees": 0,
          "spouse_value_rupees": 0,
          "huf_value_rupees": 0,
          "dependent1_value_rupees": 0,
          "dependent2_value_rupees": 0,
          "dependent3_value_rupees": 0,
          "total_value_rupees": 0
        },
        {
          "sr_no": null,
          "description": "GST Dues",
          "self_value_rupees": 0,
          "spouse_value_rupees": 0,
          "huf_value_rupees": 0,
          "dependent1_value_rupees": 0,
          "dependent2_value_rupees": 0,
          "dependent3_value_rupees": 0,
          "total_value_rupees": 0
        }
      ]
    },
    "profession_or_occupation": {
      "self": "Social Worker",
      "spouse": "House wife"
    },
    "sources_of_income": {
      "self": "Pension from Karnataka State Treasury and Interest Income",
      "spouse": "Interest Income",
      "dependent": "Interest Income"
    },
    "contracts_with_government_and_public_companies": {
      "candidate": "NIL",
      "spouse": "NIL",
      "dependent": "NIL",
      "huf_or_trust": "NIL",
      "partnership_firms": "NIL",
      "private_companies": "NIL"
    },
    "other_elections_info": [
      {
        "election_name": "Karnataka 2018",
        "declared_assets_rupees": 172571183,
        "declared_cases": 1
      },
      {
        "election_name": "Lok Sabha 2009",
        "declared_assets_rupees": 23638939,
        "declared_cases": 1
      }
    ]
  }
}