{
  "candidate_name": "ANNIBAL KENNEDY",
  "party": "DMK",
  "constituency": "OUPALAM",
  "state": "Puducherry",
  "status": "(Winner)",
  "affidavit_info": {
    "personal_details": {
      "s_o_d_o_w_o": "Annibal Victor",
      "age": 56,
      "voter_enrolled_in": {
        "constituency": "16-Oupalam (Pondicherry)",
        "serial_no": 246,
        "part_no": 16
      },
      "self_profession": "Real Estate Business",
      "spouse_profession": "House wife"
    },
    "summary": {
      "criminal_cases_count": 0,
      "total_assets_in_rupees": 58407282,
      "total_liabilities_in_rupees": 0
    },
    "educational_details": {
      "category": "Graduate",
      "details": "B.A.,-Tagore Arts and Sciences-Puducherry-1990"
    },
    "income_tax_details": {
      "report_status": "No Problems in Reading Affidavit Information",
      "returns": [
        {
          "relation_type": "self",
          "pan_given": true,
          "financial_year": "2020 - 2021",
          "total_income_shown_in_itr_rupees": 493530
        },
        {
          "relation_type": "self",
          "pan_given": true,
          "financial_year": "2019 - 2020",
          "total_income_shown_in_itr_rupees": 390419
        },
        {
          "relation_type": "self",
          "pan_given": true,
          "financial_year": "2018 - 2019",
          "total_income_shown_in_itr_rupees": 505475
        },
        {
          "relation_type": "spouse",
          "pan_given": true,
          "financial_year": "2020 - 2021",
          "total_income_shown_in_itr_rupees": 336605
        },
        {
          "relation_type": "spouse",
          "pan_given": true,
          "financial_year": "2019 - 2020",
          "total_income_shown_in_itr_rupees": 454800
        },
        {
          "relation_type": "spouse",
          "pan_given": true,
          "financial_year": "2018 - 2019",
          "total_income_shown_in_itr_rupees": 186945
        },
        {
          "relation_type": "huf",
          "pan_given": false,
          "financial_year": null,
          "total_income_shown_in_itr_rupees": 0
        },
        {
          "relation_type": "dependent1",
          "pan_given": false,
          "financial_year": null,
          "total_income_shown_in_itr_rupees": 0
        },
        {
          "relation_type": "dependent2",
          "pan_given": false,
          "financial_year": null,
          "total_income_shown_in_itr_rupees": 0
        },
        {
          "relation_type": "dependent3",
          "pan_given": false,
          "financial_year": null,
          "total_income_shown_in_itr_rupees": 0
        }
      ]
    },
    "criminal_cases": {
      "report_status": "No Problems in Reading Affidavit Information",
      "brief_details_ipc_bns": [],
      "pending_cases": [],
      "convicted_cases": []
    },
    "movable_assets": {
      "report_status": "No Problems in Reading Affidavit Information",
      "gross_total_value_self_rupees": 7698213,
      "gross_total_value_spouse_rupees": 10504068,
      "gross_total_value_huf_rupees": 0,
      "gross_total_value_dependent1_rupees": 0,
      "gross_total_value_dependent2_rupees": 0,
      "gross_total_value_dependent3_rupees": 0,
      "gross_total_value_total_rupees": 18202281,
      "items": [
        {
          "sr_no": "i",
          "description": "Cash",
          "self_value_rupees": 100000,
          "spouse_value_rupees": 50000,
          "huf_value_rupees": 0,
          "dependent1_value_rupees": 0,
          "dependent2_value_rupees": 0,
          "dependent3_value_rupees": 0,
          "total_value_rupees": 150000,
          "self_details": {
            "amount_rupees": 100000
          },
          "spouse_details": {
            "amount_rupees": 50000
          }
        },
        {
          "sr_no": "ii",
          "description": "Deposits in Banks, Financial Institutions and Non-Banking Financial Companies",
          "self_value_rupees": 5738213,
          "spouse_value_rupees": 6854318,
          "huf_value_rupees": 0,
          "dependent1_value_rupees": 0,
          "dependent2_value_rupees": 0,
          "dependent3_value_rupees": 0,
          "total_value_rupees": 12592531,
          "self_details": [
            {
              "bank": "Indian bank",
              "account_no": "642616xxxxx",
              "amount_rupees": 18463
            },
            {
              "bank": "UCO bank",
              "account_no": "0059010042xxxxx",
              "amount_rupees": 5368543
            },
            {
              "bank": "Puthvai bharayaru village bank",
              "account_no": "9581xxxxx",
              "amount_rupees": 351207
            }
          ],
          "spouse_details": [
            {
              "bank": "Indian bank",
              "account_no": "636891xxxxx",
              "amount_rupees": 261913
            },
            {
              "bank": "The pondicherry state co-op bank ltd",
              "account_no": "20209xxxxx",
              "amount_rupees": 6093716
            },
            {
              "bank": "Puthuvai bharathyaru grama bank",
              "account_no": "9315xxxxx",
              "amount_rupees": 312508
            },
            {
              "bank": "KVB bank",
              "account_no": "123017700000xxxxx",
              "amount_rupees": 187181
            }
          ]
        },
        {
          "sr_no": "iii",
          "description": "Bonds, Debentures and Shares in companies",
          "self_value_rupees": 0,
          "spouse_value_rupees": 0,
          "huf_value_rupees": 0,
          "dependent1_value_rupees": 0,
          "dependent2_value_rupees": 0,
          "dependent3_value_rupees": 0,
          "total_value_rupees": 0,
          "self_details": "Nil",
          "spouse_details": "Nil"
        },
        {
          "sr_no": "iv",
          "description": "(a) NSS, Postal Savings etc",
          "self_value_rupees": 0,
          "spouse_value_rupees": 0,
          "huf_value_rupees": 0,
          "dependent1_value_rupees": 0,
          "dependent2_value_rupees": 0,
          "dependent3_value_rupees": 0,
          "total_value_rupees": 0,
          "self_details": "Nil",
          "spouse_details": "Nil"
        },
        {
          "sr_no": null,
          "description": "(b) LIC or other insurance Policies",
          "self_value_rupees": 1500000,
          "spouse_value_rupees": 1000000,
          "huf_value_rupees": 0,
          "dependent1_value_rupees": 0,
          "dependent2_value_rupees": 0,
          "dependent3_value_rupees": 0,
          "total_value_rupees": 2500000,
          "self_details": [
            {
              "policy": "LIC police",
              "policy_no": "73658xxxxx",
              "amount_rupees": 1000000
            },
            {
              "policy": "LIC police",
              "policy_no": "73658xxxxx",
              "amount_rupees": 500000
            }
          ],
          "spouse_details": [
            {
              "policy": "LIC police",
              "policy_no": "73658xxxxx",
              "amount_rupees": 1000000
            }
          ]
        },
        {
          "sr_no": "v",
          "description": "Personal loans/advance given",
          "self_value_rupees": 0,
          "spouse_value_rupees": 0,
          "huf_value_rupees": 0,
          "dependent1_value_rupees": 0,
          "dependent2_value_rupees": 0,
          "dependent3_value_rupees": 0,
          "total_value_rupees": 0,
          "self_details": "Nil",
          "spouse_details": "Nil"
        },
        {
          "sr_no": "vi",
          "description": "Motor Vehicles (details of make, etc.)",
          "self_value_rupees": 0,
          "spouse_value_rupees": 798750,
          "huf_value_rupees": 0,
          "dependent1_value_rupees": 0,
          "dependent2_value_rupees": 0,
          "dependent3_value_rupees": 0,
          "total_value_rupees": 798750,
          "self_details": "Nil",
          "spouse_details": [
            {
              "make": "Tootaa innova car",
              "registration_no": "PY-01-CB-6667",
              "year": "2014/02/12",
              "amount_rupees": 728750
            },
            {
              "make": "Suzukiaccess",
              "registration_no": "PY-01-CU-8188",
              "year": "2019/06/04",
              "amount_rupees": 70000
            }
          ]
        },
        {
          "sr_no": "vii",
          "description": "Jewellery (give details weight value)",
          "self_value_rupees": 360000,
          "spouse_value_rupees": 1800000,
          "huf_value_rupees": 0,
          "dependent1_value_rupees": 0,
          "dependent2_value_rupees": 0,
          "dependent3_value_rupees": 0,
          "total_value_rupees": 2160000,
          "self_details": {
            "item": "Gold",
            "weight_gm": 90,
            "value_rupees": 360000
          },
          "spouse_details": {
            "item": "Gold",
            "weight_gm": 450,
            "value_rupees": 1800000
          }
        },
        {
          "sr_no": "viii",
          "description": "Other assets, such as values of claims / interests",
          "self_value_rupees": 0,
          "spouse_value_rupees": 0,
          "huf_value_rupees": 0,
          "dependent1_value_rupees": 0,
          "dependent2_value_rupees": 0,
          "dependent3_value_rupees": 0,
          "total_value_rupees": 0,
          "self_details": "Nil",
          "spouse_details": "Nil"
        }
      ]
    },
    "immovable_assets": {
      "report_status": "No Problems in Reading Affidavit Information",
      "total_current_market_value_self_rupees": 5500000,
      "total_current_market_value_spouse_rupees": 34855000,
      "total_current_market_value_huf_rupees": 0,
      "total_current_market_value_dependent1_rupees": 0,
      "total_current_market_value_dependent2_rupees": 0,
      "total_current_market_value_dependent3_rupees": 0,
      "total_current_market_value_total_rupees": 40355000,
      "items": [
        {
          "sr_no": "i",
          "description": "Agricultural Land",
          "self_value_rupees": 0,
          "spouse_value_rupees": 14500000,
          "huf_value_rupees": 0,
          "dependent1_value_rupees": 0,
          "dependent2_value_rupees": 0,
          "dependent3_value_rupees": 0,
          "total_value_rupees": 14500000,
          "self_details": "Nil",
          "spouse_details": [
            {
              "location": "Tamil nadu thiruvanamalai pavithiram village",
              "r_s_no": "6/4B,70/8,70/9",
              "total_area": "98 cent",
              "built_up_area": null,
              "inherited": false,
              "purchase_date": "2014-02-19",
              "purchase_cost_rupees": 300000,
              "development_cost_rupees": 0,
              "current_value_rupees": 2500000
            },
            {
              "location": "Puducherry,Villiyanur othiyapatti village",
              "r_s_no": "267/7,267/8",
              "total_area": "1 ac 50 cent",
              "built_up_area": null,
              "inherited": false,
              "purchase_date": "2006-02-07",
              "purchase_cost_rupees": 440000,
              "development_cost_rupees": 0,
              "current_value_rupees": 6000000
            },
            {
              "location": "Puducherry,bagui manapatti village",
              "r_s_no": "96/2",
              "total_area": "41 ac 2",
              "built_up_area": null,
              "inherited": false,
              "purchase_date": "2013-04-22",
              "purchase_cost_rupees": 1162000,
              "development_cost_rupees": 0,
              "current_value_rupees": 2000000
            },
            {
              "location": "Puducherry,bagui manapatti village",
              "r_s_no": "96/1",
              "total_area": "30000sq ft",
              "built_up_area": null,
              "inherited": false,
              "purchase_date": "2010-07-06",
              "purchase_cost_rupees": 660000,
              "development_cost_rupees": 0,
              "current_value_rupees": 4000000
            }
          ]
        },
        {
          "sr_no": "ii",
          "description": "Non Agricultural Land",
          "self_value_rupees": 4000000,
          "spouse_value_rupees": 8805000,
          "huf_value_rupees": 0,
          "dependent1_value_rupees": 0,
          "dependent2_value_rupees": 0,
          "dependent3_value_rupees": 0,
          "total_value_rupees": 12805000,
          "self_details": [
            {
              "location": "avalakuppam village",
              "r_s_no": "2/5,pl.no.23,25,26,38,39,43,44 & 45",
              "total_area": "1100 sq ft",
              "built_up_area": null,
              "inherited": false,
              "purchase_date": "1989-04-12",
              "purchase_cost_rupees": 50000,
              "development_cost_rupees": 0,
              "current_value_rupees": 4000000
            }
          ],
          "spouse_details": [
            {
              "location": "Puducherry kalaikudi thirunallur megalasagarukudi village",
              "r_s_no": "144/5A",
              "total_area": "30000 sq ft",
              "built_up_area": null,
              "inherited": false,
              "purchase_date": "2010-07-06",
              "purchase_cost_rupees": 660000,
              "development_cost_rupees": 0,
              "current_value_rupees": 1200000
            },
            {
              "location": "uducherry ulavaruikkari pillayaru savadi village",
              "r_s_no": "147/13",
              "total_area": "4299 sq ft",
              "built_up_area": null,
              "inherited": false,
              "purchase_date": "2016-06-20",
              "purchase_cost_rupees": 0,
              "development_cost_rupees": 1980000,
              "current_value_rupees": 2100000
            },
            {
              "location": "Puducherry bagui village",
              "r_s_no": "338/2,341/2,340/2 plot no.52,53",
              "total_area": "2520sq ft",
              "built_up_area": null,
              "inherited": false,
              "purchase_date": "2011-01-31",
              "purchase_cost_rupees": 0,
              "development_cost_rupees": 430000,
              "current_value_rupees": 600000
            },
            {
              "location": "Puducherry ulavaruikkari kalaipattu village",
              "r_s_no": "39/5",
              "total_area": "2700 sq ft",
              "built_up_area": null,
              "inherited": false,
              "purchase_date": "2005-06-22",
              "purchase_cost_rupees": 41000,
              "development_cost_rupees": 0,
              "current_value_rupees": 200000
            },
            {
              "location": "Puducherry karaikalu thirunallaru melakkasaikudi village",
              "r_s_no": "144/1",
              "total_area": "1288sq ft",
              "built_up_area": null,
              "inherited": false,
              "purchase_date": "2016-10-14",
              "purchase_cost_rupees": 27000,
              "development_cost_rupees": 0,
              "current_value_rupees": 105000
            },
            {
              "location": "Puducherry villuyanur uthiyapattu village",
              "r_s_no": "129/2",
              "total_area": "2650 sq ft",
              "built_up_area": null,
              "inherited": false,
              "purchase_date": "2008-03-31",
              "purchase_cost_rupees": 215000,
              "development_cost_rupees": 0,
              "current_value_rupees": 600000
            },
            {
              "location": "uducherry villuyanur uthiyapattu village",
              "r_s_no": "1292,132/5,131/2,130/2",
              "total_area": "4747 sq ft",
              "built_up_area": null,
              "inherited": false,
              "purchase_date": "2006-07-31",
              "purchase_cost_rupees": 25000,
              "development_cost_rupees": 0,
              "current_value_rupees": 700000
            },
            {
              "location": "uducherry bagui pillayarukuppam village",
              "r_s_no": "160/10pt.,94/1A,1B, plot no.86,87",
              "total_area": "2571sq ft",
              "built_up_area": null,
              "inherited": false,
              "purchase_date": "2009-02-11",
              "purchase_cost_rupees": 50000,
              "development_cost_rupees": 0,
              "current_value_rupees": 600000
            },
            {
              "location": "Puducherry puthvai village netaij nagar ward F,block-7",
              "t_s_no": "1/4,plot no.3",
              "total_area": "1800 sq ft",
              "built_up_area": null,
              "inherited": false,
              "purchase_date": "2014-07-16",
              "purchase_cost_rupees": 2880000,
              "development_cost_rupees": 0,
              "current_value_rupees": 3000000
            }
          ]
        },
        {
          "sr_no": "iii",
          "description": "Commercial Buildings",
          "self_value_rupees": 0,
          "spouse_value_rupees": 0,
          "huf_value_rupees": 0,
          "dependent1_value_rupees": 0,
          "dependent2_value_rupees": 0,
          "dependent3_value_rupees": 0,
          "total_value_rupees": 0,
          "self_details": "Nil",
          "spouse_details": "Nil"
        },
        {
          "sr_no": "iv",
          "description": "Residential Buildings",
          "self_value_rupees": 1500000,
          "spouse_value_rupees": 11250000,
          "huf_value_rupees": 0,
          "dependent1_value_rupees": 0,
          "dependent2_value_rupees": 0,
          "dependent3_value_rupees": 0,
          "total_value_rupees": 12750000,
          "self_details": [
            {
              "location": "Tnidivan vanuir koittakuppam",
              "r_s_no": "298/1",
              "total_area": "1000 sq ft",
              "built_up_area": "800 sq ft",
              "inherited": false,
              "purchase_date": "1991-01-10",
              "purchase_cost_rupees": 125000,
              "development_cost_rupees": 0,
              "current_value_rupees": 1500000
            }
          ],
          "spouse_details": [
            {
              "location": "Puducherry state puthuvai village",
              "r_s_no": "239pt",
              "total_area": "261 sq ft",
              "built_up_area": "300 sq ft",
              "inherited": false,
              "purchase_date": "2012-02-21",
              "purchase_cost_rupees": 1050000,
              "development_cost_rupees": 0,
              "current_value_rupees": 1250000
            },
            {
              "location": "Puducherry state puthuvai village",
              "r_s_no": "239pt",
              "total_area": "261 sq ft",
              "built_up_area": "900 sq ft",
              "inherited": false,
              "purchase_date": "2016-04-21",
              "purchase_cost_rupees": 4700000,
              "development_cost_rupees": 0,
              "current_value_rupees": 5000000
            },
            {
              "location": "Puducherry state puthuvai village",
              "r_s_no": "239pt",
              "total_area": "261 sq ft",
              "built_up_area": "900 sq ft",
              "inherited": false,
              "purchase_date": "2016-03-28",
              "purchase_cost_rupees": 4700000,
              "development_cost_rupees": 0,
              "current_value_rupees": 5000000
            }
          ]
        },
        {
          "sr_no": "v",
          "description": "Others",
          "self_value_rupees": 0,
          "spouse_value_rupees": 0,
          "huf_value_rupees": 0,
          "dependent1_value_rupees": 0,
          "dependent2_value_rupees": 0,
          "dependent3_value_rupees": 0,
          "total_value_rupees": 0,
          "self_details": "Nil",
          "spouse_details": "Nil"
        }
      ]
    },
    "liabilities": {
      "report_status": "No Problems in Reading Affidavit Information",
      "grand_total_of_liabilities_self_rupees": 0,
      "grand_total_of_liabilities_spouse_rupees": 0,
      "grand_total_of_liabilities_huf_rupees": 0,
      "grand_total_of_liabilities_dependent1_rupees": 0,
      "grand_total_of_liabilities_dependent2_rupees": 0,
      "grand_total_of_liabilities_dependent3_rupees": 0,
      "grand_total_of_liabilities_total_rupees": 0,
      "grand_total_of_all_govt_dues_self_rupees": 0,
      "grand_total_of_all_govt_dues_spouse_rupees": 0,
      "grand_total_of_all_govt_dues_huf_rupees": 0,
      "grand_total_of_all_govt_dues_dependent1_rupees": 0,
      "grand_total_of_all_govt_dues_dependent2_rupees": 0,
      "grand_total_of_all_govt_dues_dependent3_rupees": 0,
      "grand_total_of_all_govt_dues_total_rupees": 0,
      "any_other_liabilities_in_dispute": {
        "self_amount_rupees": 0,
        "spouse_amount_rupees": 0,
        "huf_amount_rupees": 0,
        "dependent1_amount_rupees": 0,
        "dependent2_amount_rupees": 0,
        "dependent3_amount_rupees": 0,
        "total_amount_rupees": 0,
        "details": []
      },
      "items": [
        {
          "sr_no": "i",
          "description": "Loans from Banks / FIs",
          "self_value_rupees": 0,
          "spouse_value_rupees": 0,
          "huf_value_rupees": 0,
          "dependent1_value_rupees": 0,
          "dependent2_value_rupees": 0,
          "dependent3_value_rupees": 0,
          "total_value_rupees": 0,
          "self_details": "Nil",
          "spouse_details": "Nil"
        },
        {
          "sr_no": null,
          "description": "Loans due to Individual / Entity",
          "self_value_rupees": 0,
          "spouse_value_rupees": 0,
          "huf_value_rupees": 0,
          "dependent1_value_rupees": 0,
          "dependent2_value_rupees": 0,
          "dependent3_value_rupees": 0,
          "total_value_rupees": 0,
          "self_details": "Nil",
          "spouse_details": "Nil"
        },
        {
          "sr_no": null,
          "description": "Any other Liability",
          "self_value_rupees": 0,
          "spouse_value_rupees": 0,
          "huf_value_rupees": 0,
          "dependent1_value_rupees": 0,
          "dependent2_value_rupees": 0,
          "dependent3_value_rupees": 0,
          "total_value_rupees": 0,
          "self_details": "Nil",
          "spouse_details": "Nil"
        },
        {
          "sr_no": "ii",
          "description": "Dues to departments dealing with government accommodation",
          "self_value_rupees": 0,
          "spouse_value_rupees": 0,
          "huf_value_rupees": 0,
          "dependent1_value_rupees": 0,
          "dependent2_value_rupees": 0,
          "dependent3_value_rupees": 0,
          "total_value_rupees": 0,
          "self_details": "Nil",
          "spouse_details": "Nil"
        },
        {
          "sr_no": null,
          "description": "Dues to departments dealing with supply of water",
          "self_value_rupees": 0,
          "spouse_value_rupees": 0,
          "huf_value_rupees": 0,
          "dependent1_value_rupees": 0,
          "dependent2_value_rupees": 0,
          "dependent3_value_rupees": 0,
          "total_value_rupees": 0,
          "self_details": "Nil",
          "spouse_details": "Nil"
        },
        {
          "sr_no": null,
          "description": "Dues to departments dealing with supply of electricity",
          "self_value_rupees": 0,
          "spouse_value_rupees": 0,
          "huf_value_rupees": 0,
          "dependent1_value_rupees": 0,
          "dependent2_value_rupees": 0,
          "dependent3_value_rupees": 0,
          "total_value_rupees": 0,
          "self_details": "Nil",
          "spouse_details": "Nil"
        },
        {
          "sr_no": null,
          "description": "Dues to departments dealing with telephones",
          "self_value_rupees": 0,
          "spouse_value_rupees": 0,
          "huf_value_rupees": 0,
          "dependent1_value_rupees": 0,
          "dependent2_value_rupees": 0,
          "dependent3_value_rupees": 0,
          "total_value_rupees": 0,
          "self_details": "Nil",
          "spouse_details": "Nil"
        },
        {
          "sr_no": null,
          "description": "Dues to departments dealing with supply of transport",
          "self_value_rupees": 0,
          "spouse_value_rupees": 0,
          "huf_value_rupees": 0,
          "dependent1_value_rupees": 0,
          "dependent2_value_rupees": 0,
          "dependent3_value_rupees": 0,
          "total_value_rupees": 0,
          "self_details": "Nil",
          "spouse_details": "Nil"
        },
        {
          "sr_no": null,
          "description": "Income Tax Dues",
          "self_value_rupees": 0,
          "spouse_value_rupees": 0,
          "huf_value_rupees": 0,
          "dependent1_value_rupees": 0,
          "dependent2_value_rupees": 0,
          "dependent3_value_rupees": 0,
          "total_value_rupees": 0,
          "self_details": "Nil",
          "spouse_details": "Nil"
        },
        {
          "sr_no": null,
          "description": "Wealth Tax Dues",
          "self_value_rupees": 0,
          "spouse_value_rupees": 0,
          "huf_value_rupees": 0,
          "dependent1_value_rupees": 0,
          "dependent2_value_rupees": 0,
          "dependent3_value_rupees": 0,
          "total_value_rupees": 0,
          "self_details": "Nil",
          "spouse_details": "Nil"
        },
        {
          "sr_no": null,
          "description": "Service Tax Dues",
          "self_value_rupees": 0,
          "spouse_value_rupees": 0,
          "huf_value_rupees": 0,
          "dependent1_value_rupees": 0,
          "dependent2_value_rupees": 0,
          "dependent3_value_rupees": 0,
          "total_value_rupees": 0,
          "self_details": "Nil",
          "spouse_details": "Nil"
        },
        {
          "sr_no": null,
          "description": "Property Tax Dues",
          "self_value_rupees": 0,
          "spouse_value_rupees": 0,
          "huf_value_rupees": 0,
          "dependent1_value_rupees": 0,
          "dependent2_value_rupees": 0,
          "dependent3_value_rupees": 0,
          "total_value_rupees": 0,
          "self_details": "Nil",
          "spouse_details": "Nil"
        },
        {
          "sr_no": null,
          "description": "Sales Tax Dues",
          "self_value_rupees": 0,
          "spouse_value_rupees": 0,
          "huf_value_rupees": 0,
          "dependent1_value_rupees": 0,
          "dependent2_value_rupees": 0,
          "dependent3_value_rupees": 0,
          "total_value_rupees": 0,
          "self_details": "Nil",
          "spouse_details": "Nil"
        },
        {
          "sr_no": null,
          "description": "GST Dues",
          "self_value_rupees": 0,
          "spouse_value_rupees": 0,
          "huf_value_rupees": 0,
          "dependent1_value_rupees": 0,
          "dependent2_value_rupees": 0,
          "dependent3_value_rupees": 0,
          "total_value_rupees": 0,
          "self_details": "Nil",
          "spouse_details": "Nil"
        },
        {
          "sr_no": null,
          "description": "Any Other Dues",
          "self_value_rupees": 0,
          "spouse_value_rupees": 0,
          "huf_value_rupees": 0,
          "dependent1_value_rupees": 0,
          "dependent2_value_rupees": 0,
          "dependent3_value_rupees": 0,
          "total_value_rupees": 0,
          "self_details": "Nil",
          "spouse_details": "Nil"
        }
      ]
    },
    "profession_or_occupation": {
      "self": "Real Estate Business",
      "spouse": "House wife"
    },
    "sources_of_income": {
      "self": "Real Estate Business",
      "spouse": "Nil",
      "dependent": "Nil"
    },
    "contracts_with_government_and_public_companies": {
      "candidate": "Nil",
      "spouse": "Nil",
      "dependent": "Nil",
      "huf_or_trust": "Nil",
      "partnership_firms": "Nil",
      "private_companies": "Nil"
    },
    "other_elections": [
      {
        "election": "Puducherry 2016",
        "declared_assets_rupees": 32059105,
        "declared_cases": 0
      },
      {
        "election": "Puducherry 2011",
        "declared_assets_rupees": 19019560,
        "declared_cases": 0
      },
      {
        "election": "Pondicherry 2006",
        "declared_assets_rupees": 6052592,
        "declared_cases": 0
      }
    ]
  }
}